{
  "nightly": {
    "linux": [
      {
        "python_version": "3.10",
        "gpu_arch_type": "cpu",
        "gpu_arch_version": "",
        "desired_cuda": "cpu",
        "container_image": "pytorch/manylinux2_28-builder:cpu",
        "package_type": "manywheel",
        "build_name": "manywheel-py3_10-cpu",
        "validation_runner": "linux.2xlarge",
        "installation": "pip3 install --pre torch torchvision --index-url https://download.pytorch.org/whl/nightly/cpu",
        "channel": "nightly",
        "upload_to_base_bucket": "no",
        "stable_version": "2.9.0"
      },
      {
        "python_version": "3.10",
        "gpu_arch_type": "cuda",
        "gpu_arch_version": "12.6",
        "desired_cuda": "cu126",
        "container_image": "pytorch/manylinux2_28-builder:cuda12.6",
        "package_type": "manywheel",
        "build_name": "manywheel-py3_10-cuda12_6",
        "validation_runner": "linux.g5.4xlarge.nvidia.gpu",
        "installation": "pip3 install --pre torch torchvision --index-url https://download.pytorch.org/whl/nightly/cu126",
        "channel": "nightly",
        "upload_to_base_bucket": "no",
        "stable_version": "2.9.0"
      },
      {
        "python_version": "3.10",
        "gpu_arch_type": "cuda",
        "gpu_arch_version": "12.8",
        "desired_cuda": "cu128",
        "container_image": "pytorch/manylinux2_28-builder:cuda12.8",
        "package_type": "manywheel",
        "build_name": "manywheel-py3_10-cuda12_8",
        "validation_runner": "linux.g5.4xlarge.nvidia.gpu",
        "installation": "pip3 install --pre torch torchvision --index-url https://download.pytorch.org/whl/nightly/cu128",
        "channel": "nightly",
        "upload_to_base_bucket": "no",
        "stable_version": "2.9.0"
      },
      {
        "python_version": "3.10",
        "gpu_arch_type": "cuda",
        "gpu_arch_version": "13.0",
        "desired_cuda": "cu130",
        "container_image": "pytorch/manylinux2_28-builder:cuda13.0",
        "package_type": "manywheel",
        "build_name": "manywheel-py3_10-cuda13_0",
        "validation_runner": "linux.g5.4xlarge.nvidia.gpu",
        "installation": "pip3 install --pre torch torchvision --index-url https://download.pytorch.org/whl/nightly/cu130",
        "channel": "nightly",
        "upload_to_base_bucket": "no",
        "stable_version": "2.9.0"
      },
      {
        "python_version": "3.10",
        "gpu_arch_type": "rocm",
        "gpu_arch_version": "6.4",
        "desired_cuda": "rocm6.4",
        "container_image": "pytorch/manylinux2_28-builder:rocm6.4",
        "package_type": "manywheel",
        "build_name": "manywheel-py3_10-rocm6_4",
        "validation_runner": "linux.2xlarge",
        "installation": "pip3 install --pre torch torchvision --index-url https://download.pytorch.org/whl/nightly/rocm6.4",
        "channel": "nightly",
        "upload_to_base_bucket": "no",
        "stable_version": "2.9.0"
      },
      {
        "python_version": "3.10",
        "gpu_arch_type": "rocm",
        "gpu_arch_version": "7.0",
        "desired_cuda": "rocm7.0",
        "container_image": "pytorch/manylinux2_28-builder:rocm7.0",
        "package_type": "manywheel",
        "build_name": "manywheel-py3_10-rocm7_0",
        "validation_runner": "linux.2xlarge",
        "installation": "pip3 install --pre torch torchvision --index-url https://download.pytorch.org/whl/nightly/rocm7.0",
        "channel": "nightly",
        "upload_to_base_bucket": "no",
        "stable_version": "2.9.0"
      },
      {
        "python_version": "3.11",
        "gpu_arch_type": "cpu",
        "gpu_arch_version": "",
        "desired_cuda": "cpu",
        "container_image": "pytorch/manylinux2_28-builder:cpu",
        "package_type": "manywheel",
        "build_name": "manywheel-py3_11-cpu",
        "validation_runner": "linux.2xlarge",
        "installation": "pip3 install --pre torch torchvision --index-url https://download.pytorch.org/whl/nightly/cpu",
        "channel": "nightly",
        "upload_to_base_bucket": "no",
        "stable_version": "2.9.0"
      },
      {
        "python_version": "3.11",
        "gpu_arch_type": "cuda",
        "gpu_arch_version": "12.6",
        "desired_cuda": "cu126",
        "container_image": "pytorch/manylinux2_28-builder:cuda12.6",
        "package_type": "manywheel",
        "build_name": "manywheel-py3_11-cuda12_6",
        "validation_runner": "linux.g5.4xlarge.nvidia.gpu",
        "installation": "pip3 install --pre torch torchvision --index-url https://download.pytorch.org/whl/nightly/cu126",
        "channel": "nightly",
        "upload_to_base_bucket": "no",
        "stable_version": "2.9.0"
      },
      {
        "python_version": "3.11",
        "gpu_arch_type": "cuda",
        "gpu_arch_version": "12.8",
        "desired_cuda": "cu128",
        "container_image": "pytorch/manylinux2_28-builder:cuda12.8",
        "package_type": "manywheel",
        "build_name": "manywheel-py3_11-cuda12_8",
        "validation_runner": "linux.g5.4xlarge.nvidia.gpu",
        "installation": "pip3 install --pre torch torchvision --index-url https://download.pytorch.org/whl/nightly/cu128",
        "channel": "nightly",
        "upload_to_base_bucket": "no",
        "stable_version": "2.9.0"
      },
      {
        "python_version": "3.11",
        "gpu_arch_type": "cuda",
        "gpu_arch_version": "13.0",
        "desired_cuda": "cu130",
        "container_image": "pytorch/manylinux2_28-builder:cuda13.0",
        "package_type": "manywheel",
        "build_name": "manywheel-py3_11-cuda13_0",
        "validation_runner": "linux.g5.4xlarge.nvidia.gpu",
        "installation": "pip3 install --pre torch torchvision --index-url https://download.pytorch.org/whl/nightly/cu130",
        "channel": "nightly",
        "upload_to_base_bucket": "no",
        "stable_version": "2.9.0"
      },
      {
        "python_version": "3.11",
        "gpu_arch_type": "rocm",
        "gpu_arch_version": "6.4",
        "desired_cuda": "rocm6.4",
        "container_image": "pytorch/manylinux2_28-builder:rocm6.4",
        "package_type": "manywheel",
        "build_name": "manywheel-py3_11-rocm6_4",
        "validation_runner": "linux.2xlarge",
        "installation": "pip3 install --pre torch torchvision --index-url https://download.pytorch.org/whl/nightly/rocm6.4",
        "channel": "nightly",
        "upload_to_base_bucket": "no",
        "stable_version": "2.9.0"
      },
      {
        "python_version": "3.11",
        "gpu_arch_type": "rocm",
        "gpu_arch_version": "7.0",
        "desired_cuda": "rocm7.0",
        "container_image": "pytorch/manylinux2_28-builder:rocm7.0",
        "package_type": "manywheel",
        "build_name": "manywheel-py3_11-rocm7_0",
        "validation_runner": "linux.2xlarge",
        "installation": "pip3 install --pre torch torchvision --index-url https://download.pytorch.org/whl/nightly/rocm7.0",
        "channel": "nightly",
        "upload_to_base_bucket": "no",
        "stable_version": "2.9.0"
      },
      {
        "python_version": "3.12",
        "gpu_arch_type": "cpu",
        "gpu_arch_version": "",
        "desired_cuda": "cpu",
        "container_image": "pytorch/manylinux2_28-builder:cpu",
        "package_type": "manywheel",
        "build_name": "manywheel-py3_12-cpu",
        "validation_runner": "linux.2xlarge",
        "installation": "pip3 install --pre torch torchvision --index-url https://download.pytorch.org/whl/nightly/cpu",
        "channel": "nightly",
        "upload_to_base_bucket": "no",
        "stable_version": "2.9.0"
      },
      {
        "python_version": "3.12",
        "gpu_arch_type": "cuda",
        "gpu_arch_version": "12.6",
        "desired_cuda": "cu126",
        "container_image": "pytorch/manylinux2_28-builder:cuda12.6",
        "package_type": "manywheel",
        "build_name": "manywheel-py3_12-cuda12_6",
        "validation_runner": "linux.g5.4xlarge.nvidia.gpu",
        "installation": "pip3 install --pre torch torchvision --index-url https://download.pytorch.org/whl/nightly/cu126",
        "channel": "nightly",
        "upload_to_base_bucket": "no",
        "stable_version": "2.9.0"
      },
      {
        "python_version": "3.12",
        "gpu_arch_type": "cuda",
        "gpu_arch_version": "12.8",
        "desired_cuda": "cu128",
        "container_image": "pytorch/manylinux2_28-builder:cuda12.8",
        "package_type": "manywheel",
        "build_name": "manywheel-py3_12-cuda12_8",
        "validation_runner": "linux.g5.4xlarge.nvidia.gpu",
        "installation": "pip3 install --pre torch torchvision --index-url https://download.pytorch.org/whl/nightly/cu128",
        "channel": "nightly",
        "upload_to_base_bucket": "no",
        "stable_version": "2.9.0"
      },
      {
        "python_version": "3.12",
        "gpu_arch_type": "cuda",
        "gpu_arch_version": "13.0",
        "desired_cuda": "cu130",
        "container_image": "pytorch/manylinux2_28-builder:cuda13.0",
        "package_type": "manywheel",
        "build_name": "manywheel-py3_12-cuda13_0",
        "validation_runner": "linux.g5.4xlarge.nvidia.gpu",
        "installation": "pip3 install --pre torch torchvision --index-url https://download.pytorch.org/whl/nightly/cu130",
        "channel": "nightly",
        "upload_to_base_bucket": "no",
        "stable_version": "2.9.0"
      },
      {
        "python_version": "3.12",
        "gpu_arch_type": "rocm",
        "gpu_arch_version": "6.4",
        "desired_cuda": "rocm6.4",
        "container_image": "pytorch/manylinux2_28-builder:rocm6.4",
        "package_type": "manywheel",
        "build_name": "manywheel-py3_12-rocm6_4",
        "validation_runner": "linux.2xlarge",
        "installation": "pip3 install --pre torch torchvision --index-url https://download.pytorch.org/whl/nightly/rocm6.4",
        "channel": "nightly",
        "upload_to_base_bucket": "no",
        "stable_version": "2.9.0"
      },
      {
        "python_version": "3.12",
        "gpu_arch_type": "rocm",
        "gpu_arch_version": "7.0",
        "desired_cuda": "rocm7.0",
        "container_image": "pytorch/manylinux2_28-builder:rocm7.0",
        "package_type": "manywheel",
        "build_name": "manywheel-py3_12-rocm7_0",
        "validation_runner": "linux.2xlarge",
        "installation": "pip3 install --pre torch torchvision --index-url https://download.pytorch.org/whl/nightly/rocm7.0",
        "channel": "nightly",
        "upload_to_base_bucket": "no",
        "stable_version": "2.9.0"
      },
      {
        "python_version": "3.13",
        "gpu_arch_type": "cpu",
        "gpu_arch_version": "",
        "desired_cuda": "cpu",
        "container_image": "pytorch/manylinux2_28-builder:cpu",
        "package_type": "manywheel",
        "build_name": "manywheel-py3_13-cpu",
        "validation_runner": "linux.2xlarge",
        "installation": "pip3 install --pre torch torchvision --index-url https://download.pytorch.org/whl/nightly/cpu",
        "channel": "nightly",
        "upload_to_base_bucket": "no",
        "stable_version": "2.9.0"
      },
      {
        "python_version": "3.13",
        "gpu_arch_type": "cuda",
        "gpu_arch_version": "12.6",
        "desired_cuda": "cu126",
        "container_image": "pytorch/manylinux2_28-builder:cuda12.6",
        "package_type": "manywheel",
        "build_name": "manywheel-py3_13-cuda12_6",
        "validation_runner": "linux.g5.4xlarge.nvidia.gpu",
        "installation": "pip3 install --pre torch torchvision --index-url https://download.pytorch.org/whl/nightly/cu126",
        "channel": "nightly",
        "upload_to_base_bucket": "no",
        "stable_version": "2.9.0"
      },
      {
        "python_version": "3.13",
        "gpu_arch_type": "cuda",
        "gpu_arch_version": "12.8",
        "desired_cuda": "cu128",
        "container_image": "pytorch/manylinux2_28-builder:cuda12.8",
        "package_type": "manywheel",
        "build_name": "manywheel-py3_13-cuda12_8",
        "validation_runner": "linux.g5.4xlarge.nvidia.gpu",
        "installation": "pip3 install --pre torch torchvision --index-url https://download.pytorch.org/whl/nightly/cu128",
        "channel": "nightly",
        "upload_to_base_bucket": "no",
        "stable_version": "2.9.0"
      },
      {
        "python_version": "3.13",
        "gpu_arch_type": "cuda",
        "gpu_arch_version": "13.0",
        "desired_cuda": "cu130",
        "container_image": "pytorch/manylinux2_28-builder:cuda13.0",
        "package_type": "manywheel",
        "build_name": "manywheel-py3_13-cuda13_0",
        "validation_runner": "linux.g5.4xlarge.nvidia.gpu",
        "installation": "pip3 install --pre torch torchvision --index-url https://download.pytorch.org/whl/nightly/cu130",
        "channel": "nightly",
        "upload_to_base_bucket": "no",
        "stable_version": "2.9.0"
      },
      {
        "python_version": "3.13",
        "gpu_arch_type": "rocm",
        "gpu_arch_version": "6.4",
        "desired_cuda": "rocm6.4",
        "container_image": "pytorch/manylinux2_28-builder:rocm6.4",
        "package_type": "manywheel",
        "build_name": "manywheel-py3_13-rocm6_4",
        "validation_runner": "linux.2xlarge",
        "installation": "pip3 install --pre torch torchvision --index-url https://download.pytorch.org/whl/nightly/rocm6.4",
        "channel": "nightly",
        "upload_to_base_bucket": "no",
        "stable_version": "2.9.0"
      },
      {
        "python_version": "3.13",
        "gpu_arch_type": "rocm",
        "gpu_arch_version": "7.0",
        "desired_cuda": "rocm7.0",
        "container_image": "pytorch/manylinux2_28-builder:rocm7.0",
        "package_type": "manywheel",
        "build_name": "manywheel-py3_13-rocm7_0",
        "validation_runner": "linux.2xlarge",
        "installation": "pip3 install --pre torch torchvision --index-url https://download.pytorch.org/whl/nightly/rocm7.0",
        "channel": "nightly",
        "upload_to_base_bucket": "no",
        "stable_version": "2.9.0"
      },
      {
        "python_version": "3.13t",
        "gpu_arch_type": "cpu",
        "gpu_arch_version": "",
        "desired_cuda": "cpu",
        "container_image": "pytorch/manylinux2_28-builder:cpu",
        "package_type": "manywheel",
        "build_name": "manywheel-py3_13t-cpu",
        "validation_runner": "linux.2xlarge",
        "installation": "pip3 install --pre torch torchvision --index-url https://download.pytorch.org/whl/nightly/cpu",
        "channel": "nightly",
        "upload_to_base_bucket": "no",
        "stable_version": "2.9.0"
      },
      {
        "python_version": "3.13t",
        "gpu_arch_type": "cuda",
        "gpu_arch_version": "12.6",
        "desired_cuda": "cu126",
        "container_image": "pytorch/manylinux2_28-builder:cuda12.6",
        "package_type": "manywheel",
        "build_name": "manywheel-py3_13t-cuda12_6",
        "validation_runner": "linux.g5.4xlarge.nvidia.gpu",
        "installation": "pip3 install --pre torch torchvision --index-url https://download.pytorch.org/whl/nightly/cu126",
        "channel": "nightly",
        "upload_to_base_bucket": "no",
        "stable_version": "2.9.0"
      },
      {
        "python_version": "3.13t",
        "gpu_arch_type": "cuda",
        "gpu_arch_version": "12.8",
        "desired_cuda": "cu128",
        "container_image": "pytorch/manylinux2_28-builder:cuda12.8",
        "package_type": "manywheel",
        "build_name": "manywheel-py3_13t-cuda12_8",
        "validation_runner": "linux.g5.4xlarge.nvidia.gpu",
        "installation": "pip3 install --pre torch torchvision --index-url https://download.pytorch.org/whl/nightly/cu128",
        "channel": "nightly",
        "upload_to_base_bucket": "no",
        "stable_version": "2.9.0"
      },
      {
        "python_version": "3.13t",
        "gpu_arch_type": "cuda",
        "gpu_arch_version": "13.0",
        "desired_cuda": "cu130",
        "container_image": "pytorch/manylinux2_28-builder:cuda13.0",
        "package_type": "manywheel",
        "build_name": "manywheel-py3_13t-cuda13_0",
        "validation_runner": "linux.g5.4xlarge.nvidia.gpu",
        "installation": "pip3 install --pre torch torchvision --index-url https://download.pytorch.org/whl/nightly/cu130",
        "channel": "nightly",
        "upload_to_base_bucket": "no",
        "stable_version": "2.9.0"
      },
      {
        "python_version": "3.13t",
        "gpu_arch_type": "rocm",
        "gpu_arch_version": "6.4",
        "desired_cuda": "rocm6.4",
        "container_image": "pytorch/manylinux2_28-builder:rocm6.4",
        "package_type": "manywheel",
        "build_name": "manywheel-py3_13t-rocm6_4",
        "validation_runner": "linux.2xlarge",
        "installation": "pip3 install --pre torch torchvision --index-url https://download.pytorch.org/whl/nightly/rocm6.4",
        "channel": "nightly",
        "upload_to_base_bucket": "no",
        "stable_version": "2.9.0"
      },
      {
        "python_version": "3.13t",
        "gpu_arch_type": "rocm",
        "gpu_arch_version": "7.0",
        "desired_cuda": "rocm7.0",
        "container_image": "pytorch/manylinux2_28-builder:rocm7.0",
        "package_type": "manywheel",
        "build_name": "manywheel-py3_13t-rocm7_0",
        "validation_runner": "linux.2xlarge",
        "installation": "pip3 install --pre torch torchvision --index-url https://download.pytorch.org/whl/nightly/rocm7.0",
        "channel": "nightly",
        "upload_to_base_bucket": "no",
        "stable_version": "2.9.0"
      },
      {
        "python_version": "3.14",
        "gpu_arch_type": "cpu",
        "gpu_arch_version": "",
        "desired_cuda": "cpu",
        "container_image": "pytorch/manylinux2_28-builder:cpu",
        "package_type": "manywheel",
        "build_name": "manywheel-py3_14-cpu",
        "validation_runner": "linux.2xlarge",
        "installation": "pip3 install --pre torch torchvision --index-url https://download.pytorch.org/whl/nightly/cpu",
        "channel": "nightly",
        "upload_to_base_bucket": "no",
        "stable_version": "2.9.0"
      },
      {
        "python_version": "3.14",
        "gpu_arch_type": "cuda",
        "gpu_arch_version": "12.6",
        "desired_cuda": "cu126",
        "container_image": "pytorch/manylinux2_28-builder:cuda12.6",
        "package_type": "manywheel",
        "build_name": "manywheel-py3_14-cuda12_6",
        "validation_runner": "linux.g5.4xlarge.nvidia.gpu",
        "installation": "pip3 install --pre torch torchvision --index-url https://download.pytorch.org/whl/nightly/cu126",
        "channel": "nightly",
        "upload_to_base_bucket": "no",
        "stable_version": "2.9.0"
      },
      {
        "python_version": "3.14",
        "gpu_arch_type": "cuda",
        "gpu_arch_version": "12.8",
        "desired_cuda": "cu128",
        "container_image": "pytorch/manylinux2_28-builder:cuda12.8",
        "package_type": "manywheel",
        "build_name": "manywheel-py3_14-cuda12_8",
        "validation_runner": "linux.g5.4xlarge.nvidia.gpu",
        "installation": "pip3 install --pre torch torchvision --index-url https://download.pytorch.org/whl/nightly/cu128",
        "channel": "nightly",
        "upload_to_base_bucket": "no",
        "stable_version": "2.9.0"
      },
      {
        "python_version": "3.14",
        "gpu_arch_type": "cuda",
        "gpu_arch_version": "13.0",
        "desired_cuda": "cu130",
        "container_image": "pytorch/manylinux2_28-builder:cuda13.0",
        "package_type": "manywheel",
        "build_name": "manywheel-py3_14-cuda13_0",
        "validation_runner": "linux.g5.4xlarge.nvidia.gpu",
        "installation": "pip3 install --pre torch torchvision --index-url https://download.pytorch.org/whl/nightly/cu130",
        "channel": "nightly",
        "upload_to_base_bucket": "no",
        "stable_version": "2.9.0"
      },
      {
        "python_version": "3.14",
        "gpu_arch_type": "rocm",
        "gpu_arch_version": "6.4",
        "desired_cuda": "rocm6.4",
        "container_image": "pytorch/manylinux2_28-builder:rocm6.4",
        "package_type": "manywheel",
        "build_name": "manywheel-py3_14-rocm6_4",
        "validation_runner": "linux.2xlarge",
        "installation": "pip3 install --pre torch torchvision --index-url https://download.pytorch.org/whl/nightly/rocm6.4",
        "channel": "nightly",
        "upload_to_base_bucket": "no",
        "stable_version": "2.9.0"
      },
      {
        "python_version": "3.14",
        "gpu_arch_type": "rocm",
        "gpu_arch_version": "7.0",
        "desired_cuda": "rocm7.0",
        "container_image": "pytorch/manylinux2_28-builder:rocm7.0",
        "package_type": "manywheel",
        "build_name": "manywheel-py3_14-rocm7_0",
        "validation_runner": "linux.2xlarge",
        "installation": "pip3 install --pre torch torchvision --index-url https://download.pytorch.org/whl/nightly/rocm7.0",
        "channel": "nightly",
        "upload_to_base_bucket": "no",
        "stable_version": "2.9.0"
      },
      {
        "python_version": "3.14t",
        "gpu_arch_type": "cpu",
        "gpu_arch_version": "",
        "desired_cuda": "cpu",
        "container_image": "pytorch/manylinux2_28-builder:cpu",
        "package_type": "manywheel",
        "build_name": "manywheel-py3_14t-cpu",
        "validation_runner": "linux.2xlarge",
        "installation": "pip3 install --pre torch torchvision --index-url https://download.pytorch.org/whl/nightly/cpu",
        "channel": "nightly",
        "upload_to_base_bucket": "no",
        "stable_version": "2.9.0"
      },
      {
        "python_version": "3.14t",
        "gpu_arch_type": "cuda",
        "gpu_arch_version": "12.6",
        "desired_cuda": "cu126",
        "container_image": "pytorch/manylinux2_28-builder:cuda12.6",
        "package_type": "manywheel",
        "build_name": "manywheel-py3_14t-cuda12_6",
        "validation_runner": "linux.g5.4xlarge.nvidia.gpu",
        "installation": "pip3 install --pre torch torchvision --index-url https://download.pytorch.org/whl/nightly/cu126",
        "channel": "nightly",
        "upload_to_base_bucket": "no",
        "stable_version": "2.9.0"
      },
      {
        "python_version": "3.14t",
        "gpu_arch_type": "cuda",
        "gpu_arch_version": "12.8",
        "desired_cuda": "cu128",
        "container_image": "pytorch/manylinux2_28-builder:cuda12.8",
        "package_type": "manywheel",
        "build_name": "manywheel-py3_14t-cuda12_8",
        "validation_runner": "linux.g5.4xlarge.nvidia.gpu",
        "installation": "pip3 install --pre torch torchvision --index-url https://download.pytorch.org/whl/nightly/cu128",
        "channel": "nightly",
        "upload_to_base_bucket": "no",
        "stable_version": "2.9.0"
      },
      {
        "python_version": "3.14t",
        "gpu_arch_type": "cuda",
        "gpu_arch_version": "13.0",
        "desired_cuda": "cu130",
        "container_image": "pytorch/manylinux2_28-builder:cuda13.0",
        "package_type": "manywheel",
        "build_name": "manywheel-py3_14t-cuda13_0",
        "validation_runner": "linux.g5.4xlarge.nvidia.gpu",
        "installation": "pip3 install --pre torch torchvision --index-url https://download.pytorch.org/whl/nightly/cu130",
        "channel": "nightly",
        "upload_to_base_bucket": "no",
        "stable_version": "2.9.0"
      },
      {
        "python_version": "3.14t",
        "gpu_arch_type": "rocm",
        "gpu_arch_version": "6.4",
        "desired_cuda": "rocm6.4",
        "container_image": "pytorch/manylinux2_28-builder:rocm6.4",
        "package_type": "manywheel",
        "build_name": "manywheel-py3_14t-rocm6_4",
        "validation_runner": "linux.2xlarge",
        "installation": "pip3 install --pre torch torchvision --index-url https://download.pytorch.org/whl/nightly/rocm6.4",
        "channel": "nightly",
        "upload_to_base_bucket": "no",
        "stable_version": "2.9.0"
      },
      {
        "python_version": "3.14t",
        "gpu_arch_type": "rocm",
        "gpu_arch_version": "7.0",
        "desired_cuda": "rocm7.0",
        "container_image": "pytorch/manylinux2_28-builder:rocm7.0",
        "package_type": "manywheel",
        "build_name": "manywheel-py3_14t-rocm7_0",
        "validation_runner": "linux.2xlarge",
        "installation": "pip3 install --pre torch torchvision --index-url https://download.pytorch.org/whl/nightly/rocm7.0",
        "channel": "nightly",
        "upload_to_base_bucket": "no",
        "stable_version": "2.9.0"
      },
      {
        "gpu_arch_type": "cpu",
        "gpu_arch_version": "",
        "desired_cuda": "cpu",
        "libtorch_variant": "shared-with-deps",
        "libtorch_config": "",
        "devtoolset": "cxx11-abi",
        "container_image": "pytorch/libtorch-cxx11-builder:cpu",
        "package_type": "libtorch",
        "build_name": "libtorch-cpu-shared-with-deps-cxx11-abi",
        "validation_runner": "linux.2xlarge",
        "installation": "https://download.pytorch.org/libtorch/nightly/cpu/libtorch-shared-with-deps-latest.zip",
        "channel": "nightly",
        "stable_version": "2.9.0"
      },
      {
        "gpu_arch_type": "cuda",
        "gpu_arch_version": "12.6",
        "desired_cuda": "cu126",
        "libtorch_variant": "shared-with-deps",
        "libtorch_config": "",
        "devtoolset": "cxx11-abi",
        "container_image": "pytorch/libtorch-cxx11-builder:cuda12.6",
        "package_type": "libtorch",
        "build_name": "libtorch-cuda12_6-shared-with-deps-cxx11-abi",
        "validation_runner": "linux.2xlarge",
        "installation": "https://download.pytorch.org/libtorch/nightly/cu126/libtorch-shared-with-deps-latest.zip",
        "channel": "nightly",
        "stable_version": "2.9.0"
      },
      {
        "gpu_arch_type": "cuda",
        "gpu_arch_version": "12.8",
        "desired_cuda": "cu128",
        "libtorch_variant": "shared-with-deps",
        "libtorch_config": "",
        "devtoolset": "cxx11-abi",
        "container_image": "pytorch/libtorch-cxx11-builder:cuda12.8",
        "package_type": "libtorch",
        "build_name": "libtorch-cuda12_8-shared-with-deps-cxx11-abi",
        "validation_runner": "linux.2xlarge",
        "installation": "https://download.pytorch.org/libtorch/nightly/cu128/libtorch-shared-with-deps-latest.zip",
        "channel": "nightly",
        "stable_version": "2.9.0"
      },
      {
        "gpu_arch_type": "cuda",
        "gpu_arch_version": "13.0",
        "desired_cuda": "cu130",
        "libtorch_variant": "shared-with-deps",
        "libtorch_config": "",
        "devtoolset": "cxx11-abi",
        "container_image": "pytorch/libtorch-cxx11-builder:cuda13.0",
        "package_type": "libtorch",
        "build_name": "libtorch-cuda13_0-shared-with-deps-cxx11-abi",
        "validation_runner": "linux.2xlarge",
        "installation": "https://download.pytorch.org/libtorch/nightly/cu130/libtorch-shared-with-deps-latest.zip",
        "channel": "nightly",
        "stable_version": "2.9.0"
      },
      {
        "gpu_arch_type": "rocm",
        "gpu_arch_version": "6.4",
        "desired_cuda": "rocm6.4",
        "libtorch_variant": "shared-with-deps",
        "libtorch_config": "",
        "devtoolset": "cxx11-abi",
        "container_image": "pytorch/libtorch-cxx11-builder:rocm6.4",
        "package_type": "libtorch",
        "build_name": "libtorch-rocm6_4-shared-with-deps-cxx11-abi",
        "validation_runner": "linux.2xlarge",
        "installation": "https://download.pytorch.org/libtorch/nightly/rocm6.4/libtorch-shared-with-deps-latest.zip",
        "channel": "nightly",
        "stable_version": "2.9.0"
      },
      {
        "gpu_arch_type": "rocm",
        "gpu_arch_version": "7.0",
        "desired_cuda": "rocm7.0",
        "libtorch_variant": "shared-with-deps",
        "libtorch_config": "",
        "devtoolset": "cxx11-abi",
        "container_image": "pytorch/libtorch-cxx11-builder:rocm7.0",
        "package_type": "libtorch",
        "build_name": "libtorch-rocm7_0-shared-with-deps-cxx11-abi",
        "validation_runner": "linux.2xlarge",
        "installation": "https://download.pytorch.org/libtorch/nightly/rocm7.0/libtorch-shared-with-deps-latest.zip",
        "channel": "nightly",
        "stable_version": "2.9.0"
      }
    ],
    "windows": [
      {
        "python_version": "3.10",
        "gpu_arch_type": "cpu",
        "gpu_arch_version": "",
        "desired_cuda": "cpu",
        "container_image": "pytorch/manylinux2_28-builder:cpu",
        "package_type": "wheel",
        "build_name": "wheel-py3_10-cpu",
        "validation_runner": "windows.4xlarge",
        "installation": "pip3 install --pre torch torchvision --index-url https://download.pytorch.org/whl/nightly/cpu",
        "channel": "nightly",
        "upload_to_base_bucket": "no",
        "stable_version": "2.9.0"
      },
      {
        "python_version": "3.10",
        "gpu_arch_type": "cuda",
        "gpu_arch_version": "12.6",
        "desired_cuda": "cu126",
        "container_image": "pytorch/manylinux2_28-builder:cuda12.6",
        "package_type": "wheel",
        "build_name": "wheel-py3_10-cuda12_6",
        "validation_runner": "windows.g4dn.xlarge",
        "installation": "pip3 install --pre torch torchvision --index-url https://download.pytorch.org/whl/nightly/cu126",
        "channel": "nightly",
        "upload_to_base_bucket": "no",
        "stable_version": "2.9.0"
      },
      {
        "python_version": "3.10",
        "gpu_arch_type": "cuda",
        "gpu_arch_version": "12.8",
        "desired_cuda": "cu128",
        "container_image": "pytorch/manylinux2_28-builder:cuda12.8",
        "package_type": "wheel",
        "build_name": "wheel-py3_10-cuda12_8",
        "validation_runner": "windows.g4dn.xlarge",
        "installation": "pip3 install --pre torch torchvision --index-url https://download.pytorch.org/whl/nightly/cu128",
        "channel": "nightly",
        "upload_to_base_bucket": "no",
        "stable_version": "2.9.0"
      },
      {
        "python_version": "3.10",
        "gpu_arch_type": "cuda",
        "gpu_arch_version": "13.0",
        "desired_cuda": "cu130",
        "container_image": "pytorch/manylinux2_28-builder:cuda13.0",
        "package_type": "wheel",
        "build_name": "wheel-py3_10-cuda13_0",
        "validation_runner": "windows.g4dn.xlarge",
        "installation": "pip3 install --pre torch torchvision --index-url https://download.pytorch.org/whl/nightly/cu130",
        "channel": "nightly",
        "upload_to_base_bucket": "no",
        "stable_version": "2.9.0"
      },
      {
        "python_version": "3.11",
        "gpu_arch_type": "cpu",
        "gpu_arch_version": "",
        "desired_cuda": "cpu",
        "container_image": "pytorch/manylinux2_28-builder:cpu",
        "package_type": "wheel",
        "build_name": "wheel-py3_11-cpu",
        "validation_runner": "windows.4xlarge",
        "installation": "pip3 install --pre torch torchvision --index-url https://download.pytorch.org/whl/nightly/cpu",
        "channel": "nightly",
        "upload_to_base_bucket": "no",
        "stable_version": "2.9.0"
      },
      {
        "python_version": "3.11",
        "gpu_arch_type": "cuda",
        "gpu_arch_version": "12.6",
        "desired_cuda": "cu126",
        "container_image": "pytorch/manylinux2_28-builder:cuda12.6",
        "package_type": "wheel",
        "build_name": "wheel-py3_11-cuda12_6",
        "validation_runner": "windows.g4dn.xlarge",
        "installation": "pip3 install --pre torch torchvision --index-url https://download.pytorch.org/whl/nightly/cu126",
        "channel": "nightly",
        "upload_to_base_bucket": "no",
        "stable_version": "2.9.0"
      },
      {
        "python_version": "3.11",
        "gpu_arch_type": "cuda",
        "gpu_arch_version": "12.8",
        "desired_cuda": "cu128",
        "container_image": "pytorch/manylinux2_28-builder:cuda12.8",
        "package_type": "wheel",
        "build_name": "wheel-py3_11-cuda12_8",
        "validation_runner": "windows.g4dn.xlarge",
        "installation": "pip3 install --pre torch torchvision --index-url https://download.pytorch.org/whl/nightly/cu128",
        "channel": "nightly",
        "upload_to_base_bucket": "no",
        "stable_version": "2.9.0"
      },
      {
        "python_version": "3.11",
        "gpu_arch_type": "cuda",
        "gpu_arch_version": "13.0",
        "desired_cuda": "cu130",
        "container_image": "pytorch/manylinux2_28-builder:cuda13.0",
        "package_type": "wheel",
        "build_name": "wheel-py3_11-cuda13_0",
        "validation_runner": "windows.g4dn.xlarge",
        "installation": "pip3 install --pre torch torchvision --index-url https://download.pytorch.org/whl/nightly/cu130",
        "channel": "nightly",
        "upload_to_base_bucket": "no",
        "stable_version": "2.9.0"
      },
      {
        "python_version": "3.12",
        "gpu_arch_type": "cpu",
        "gpu_arch_version": "",
        "desired_cuda": "cpu",
        "container_image": "pytorch/manylinux2_28-builder:cpu",
        "package_type": "wheel",
        "build_name": "wheel-py3_12-cpu",
        "validation_runner": "windows.4xlarge",
        "installation": "pip3 install --pre torch torchvision --index-url https://download.pytorch.org/whl/nightly/cpu",
        "channel": "nightly",
        "upload_to_base_bucket": "no",
        "stable_version": "2.9.0"
      },
      {
        "python_version": "3.12",
        "gpu_arch_type": "cuda",
        "gpu_arch_version": "12.6",
        "desired_cuda": "cu126",
        "container_image": "pytorch/manylinux2_28-builder:cuda12.6",
        "package_type": "wheel",
        "build_name": "wheel-py3_12-cuda12_6",
        "validation_runner": "windows.g4dn.xlarge",
        "installation": "pip3 install --pre torch torchvision --index-url https://download.pytorch.org/whl/nightly/cu126",
        "channel": "nightly",
        "upload_to_base_bucket": "no",
        "stable_version": "2.9.0"
      },
      {
        "python_version": "3.12",
        "gpu_arch_type": "cuda",
        "gpu_arch_version": "12.8",
        "desired_cuda": "cu128",
        "container_image": "pytorch/manylinux2_28-builder:cuda12.8",
        "package_type": "wheel",
        "build_name": "wheel-py3_12-cuda12_8",
        "validation_runner": "windows.g4dn.xlarge",
        "installation": "pip3 install --pre torch torchvision --index-url https://download.pytorch.org/whl/nightly/cu128",
        "channel": "nightly",
        "upload_to_base_bucket": "no",
        "stable_version": "2.9.0"
      },
      {
        "python_version": "3.12",
        "gpu_arch_type": "cuda",
        "gpu_arch_version": "13.0",
        "desired_cuda": "cu130",
        "container_image": "pytorch/manylinux2_28-builder:cuda13.0",
        "package_type": "wheel",
        "build_name": "wheel-py3_12-cuda13_0",
        "validation_runner": "windows.g4dn.xlarge",
        "installation": "pip3 install --pre torch torchvision --index-url https://download.pytorch.org/whl/nightly/cu130",
        "channel": "nightly",
        "upload_to_base_bucket": "no",
        "stable_version": "2.9.0"
      },
      {
        "python_version": "3.13",
        "gpu_arch_type": "cpu",
        "gpu_arch_version": "",
        "desired_cuda": "cpu",
        "container_image": "pytorch/manylinux2_28-builder:cpu",
        "package_type": "wheel",
        "build_name": "wheel-py3_13-cpu",
        "validation_runner": "windows.4xlarge",
        "installation": "pip3 install --pre torch torchvision --index-url https://download.pytorch.org/whl/nightly/cpu",
        "channel": "nightly",
        "upload_to_base_bucket": "no",
        "stable_version": "2.9.0"
      },
      {
        "python_version": "3.13",
        "gpu_arch_type": "cuda",
        "gpu_arch_version": "12.6",
        "desired_cuda": "cu126",
        "container_image": "pytorch/manylinux2_28-builder:cuda12.6",
        "package_type": "wheel",
        "build_name": "wheel-py3_13-cuda12_6",
        "validation_runner": "windows.g4dn.xlarge",
        "installation": "pip3 install --pre torch torchvision --index-url https://download.pytorch.org/whl/nightly/cu126",
        "channel": "nightly",
        "upload_to_base_bucket": "no",
        "stable_version": "2.9.0"
      },
      {
        "python_version": "3.13",
        "gpu_arch_type": "cuda",
        "gpu_arch_version": "12.8",
        "desired_cuda": "cu128",
        "container_image": "pytorch/manylinux2_28-builder:cuda12.8",
        "package_type": "wheel",
        "build_name": "wheel-py3_13-cuda12_8",
        "validation_runner": "windows.g4dn.xlarge",
        "installation": "pip3 install --pre torch torchvision --index-url https://download.pytorch.org/whl/nightly/cu128",
        "channel": "nightly",
        "upload_to_base_bucket": "no",
        "stable_version": "2.9.0"
      },
      {
        "python_version": "3.13",
        "gpu_arch_type": "cuda",
        "gpu_arch_version": "13.0",
        "desired_cuda": "cu130",
        "container_image": "pytorch/manylinux2_28-builder:cuda13.0",
        "package_type": "wheel",
        "build_name": "wheel-py3_13-cuda13_0",
        "validation_runner": "windows.g4dn.xlarge",
        "installation": "pip3 install --pre torch torchvision --index-url https://download.pytorch.org/whl/nightly/cu130",
        "channel": "nightly",
        "upload_to_base_bucket": "no",
        "stable_version": "2.9.0"
      },
      {
        "python_version": "3.13t",
        "gpu_arch_type": "cpu",
        "gpu_arch_version": "",
        "desired_cuda": "cpu",
        "container_image": "pytorch/manylinux2_28-builder:cpu",
        "package_type": "wheel",
        "build_name": "wheel-py3_13t-cpu",
        "validation_runner": "windows.4xlarge",
        "installation": "pip3 install --pre torch torchvision --index-url https://download.pytorch.org/whl/nightly/cpu",
        "channel": "nightly",
        "upload_to_base_bucket": "no",
        "stable_version": "2.9.0"
      },
      {
        "python_version": "3.13t",
        "gpu_arch_type": "cuda",
        "gpu_arch_version": "12.6",
        "desired_cuda": "cu126",
        "container_image": "pytorch/manylinux2_28-builder:cuda12.6",
        "package_type": "wheel",
        "build_name": "wheel-py3_13t-cuda12_6",
        "validation_runner": "windows.g4dn.xlarge",
        "installation": "pip3 install --pre torch torchvision --index-url https://download.pytorch.org/whl/nightly/cu126",
        "channel": "nightly",
        "upload_to_base_bucket": "no",
        "stable_version": "2.9.0"
      },
      {
        "python_version": "3.13t",
        "gpu_arch_type": "cuda",
        "gpu_arch_version": "12.8",
        "desired_cuda": "cu128",
        "container_image": "pytorch/manylinux2_28-builder:cuda12.8",
        "package_type": "wheel",
        "build_name": "wheel-py3_13t-cuda12_8",
        "validation_runner": "windows.g4dn.xlarge",
        "installation": "pip3 install --pre torch torchvision --index-url https://download.pytorch.org/whl/nightly/cu128",
        "channel": "nightly",
        "upload_to_base_bucket": "no",
        "stable_version": "2.9.0"
      },
      {
        "python_version": "3.13t",
        "gpu_arch_type": "cuda",
        "gpu_arch_version": "13.0",
        "desired_cuda": "cu130",
        "container_image": "pytorch/manylinux2_28-builder:cuda13.0",
        "package_type": "wheel",
        "build_name": "wheel-py3_13t-cuda13_0",
        "validation_runner": "windows.g4dn.xlarge",
        "installation": "pip3 install --pre torch torchvision --index-url https://download.pytorch.org/whl/nightly/cu130",
        "channel": "nightly",
        "upload_to_base_bucket": "no",
        "stable_version": "2.9.0"
      },
      {
        "python_version": "3.14",
        "gpu_arch_type": "cpu",
        "gpu_arch_version": "",
        "desired_cuda": "cpu",
        "container_image": "pytorch/manylinux2_28-builder:cpu",
        "package_type": "wheel",
        "build_name": "wheel-py3_14-cpu",
        "validation_runner": "windows.4xlarge",
        "installation": "pip3 install --pre torch torchvision --index-url https://download.pytorch.org/whl/nightly/cpu",
        "channel": "nightly",
        "upload_to_base_bucket": "no",
        "stable_version": "2.9.0"
      },
      {
        "python_version": "3.14",
        "gpu_arch_type": "cuda",
        "gpu_arch_version": "12.6",
        "desired_cuda": "cu126",
        "container_image": "pytorch/manylinux2_28-builder:cuda12.6",
        "package_type": "wheel",
        "build_name": "wheel-py3_14-cuda12_6",
        "validation_runner": "windows.g4dn.xlarge",
        "installation": "pip3 install --pre torch torchvision --index-url https://download.pytorch.org/whl/nightly/cu126",
        "channel": "nightly",
        "upload_to_base_bucket": "no",
        "stable_version": "2.9.0"
      },
      {
        "python_version": "3.14",
        "gpu_arch_type": "cuda",
        "gpu_arch_version": "12.8",
        "desired_cuda": "cu128",
        "container_image": "pytorch/manylinux2_28-builder:cuda12.8",
        "package_type": "wheel",
        "build_name": "wheel-py3_14-cuda12_8",
        "validation_runner": "windows.g4dn.xlarge",
        "installation": "pip3 install --pre torch torchvision --index-url https://download.pytorch.org/whl/nightly/cu128",
        "channel": "nightly",
        "upload_to_base_bucket": "no",
        "stable_version": "2.9.0"
      },
      {
        "python_version": "3.14",
        "gpu_arch_type": "cuda",
        "gpu_arch_version": "13.0",
        "desired_cuda": "cu130",
        "container_image": "pytorch/manylinux2_28-builder:cuda13.0",
        "package_type": "wheel",
        "build_name": "wheel-py3_14-cuda13_0",
        "validation_runner": "windows.g4dn.xlarge",
        "installation": "pip3 install --pre torch torchvision --index-url https://download.pytorch.org/whl/nightly/cu130",
        "channel": "nightly",
        "upload_to_base_bucket": "no",
        "stable_version": "2.9.0"
      },
      {
        "python_version": "3.14t",
        "gpu_arch_type": "cpu",
        "gpu_arch_version": "",
        "desired_cuda": "cpu",
        "container_image": "pytorch/manylinux2_28-builder:cpu",
        "package_type": "wheel",
        "build_name": "wheel-py3_14t-cpu",
        "validation_runner": "windows.4xlarge",
        "installation": "pip3 install --pre torch torchvision --index-url https://download.pytorch.org/whl/nightly/cpu",
        "channel": "nightly",
        "upload_to_base_bucket": "no",
        "stable_version": "2.9.0"
      },
      {
        "python_version": "3.14t",
        "gpu_arch_type": "cuda",
        "gpu_arch_version": "12.6",
        "desired_cuda": "cu126",
        "container_image": "pytorch/manylinux2_28-builder:cuda12.6",
        "package_type": "wheel",
        "build_name": "wheel-py3_14t-cuda12_6",
        "validation_runner": "windows.g4dn.xlarge",
        "installation": "pip3 install --pre torch torchvision --index-url https://download.pytorch.org/whl/nightly/cu126",
        "channel": "nightly",
        "upload_to_base_bucket": "no",
        "stable_version": "2.9.0"
      },
      {
        "python_version": "3.14t",
        "gpu_arch_type": "cuda",
        "gpu_arch_version": "12.8",
        "desired_cuda": "cu128",
        "container_image": "pytorch/manylinux2_28-builder:cuda12.8",
        "package_type": "wheel",
        "build_name": "wheel-py3_14t-cuda12_8",
        "validation_runner": "windows.g4dn.xlarge",
        "installation": "pip3 install --pre torch torchvision --index-url https://download.pytorch.org/whl/nightly/cu128",
        "channel": "nightly",
        "upload_to_base_bucket": "no",
        "stable_version": "2.9.0"
      },
      {
        "python_version": "3.14t",
        "gpu_arch_type": "cuda",
        "gpu_arch_version": "13.0",
        "desired_cuda": "cu130",
        "container_image": "pytorch/manylinux2_28-builder:cuda13.0",
        "package_type": "wheel",
        "build_name": "wheel-py3_14t-cuda13_0",
        "validation_runner": "windows.g4dn.xlarge",
        "installation": "pip3 install --pre torch torchvision --index-url https://download.pytorch.org/whl/nightly/cu130",
        "channel": "nightly",
        "upload_to_base_bucket": "no",
        "stable_version": "2.9.0"
      },
      {
        "gpu_arch_type": "cpu",
        "gpu_arch_version": "",
        "desired_cuda": "cpu",
        "libtorch_variant": "shared-with-deps",
        "libtorch_config": "release",
        "devtoolset": "",
        "container_image": "",
        "package_type": "libtorch",
        "build_name": "libtorch-cpu-shared-with-deps-release",
        "validation_runner": "windows.4xlarge",
        "installation": "https://download.pytorch.org/libtorch/nightly/cpu/libtorch-win-shared-with-deps-latest.zip",
        "channel": "nightly",
        "stable_version": "2.9.0"
      },
      {
        "gpu_arch_type": "cuda",
        "gpu_arch_version": "12.6",
        "desired_cuda": "cu126",
        "libtorch_variant": "shared-with-deps",
        "libtorch_config": "release",
        "devtoolset": "",
        "container_image": "",
        "package_type": "libtorch",
        "build_name": "libtorch-cuda12_6-shared-with-deps-release",
        "validation_runner": "windows.4xlarge",
        "installation": "https://download.pytorch.org/libtorch/nightly/cu126/libtorch-win-shared-with-deps-latest.zip",
        "channel": "nightly",
        "stable_version": "2.9.0"
      },
      {
        "gpu_arch_type": "cuda",
        "gpu_arch_version": "12.8",
        "desired_cuda": "cu128",
        "libtorch_variant": "shared-with-deps",
        "libtorch_config": "release",
        "devtoolset": "",
        "container_image": "",
        "package_type": "libtorch",
        "build_name": "libtorch-cuda12_8-shared-with-deps-release",
        "validation_runner": "windows.4xlarge",
        "installation": "https://download.pytorch.org/libtorch/nightly/cu128/libtorch-win-shared-with-deps-latest.zip",
        "channel": "nightly",
        "stable_version": "2.9.0"
      },
      {
        "gpu_arch_type": "cuda",
        "gpu_arch_version": "13.0",
        "desired_cuda": "cu130",
        "libtorch_variant": "shared-with-deps",
        "libtorch_config": "release",
        "devtoolset": "",
        "container_image": "",
        "package_type": "libtorch",
        "build_name": "libtorch-cuda13_0-shared-with-deps-release",
        "validation_runner": "windows.4xlarge",
        "installation": "https://download.pytorch.org/libtorch/nightly/cu130/libtorch-win-shared-with-deps-latest.zip",
        "channel": "nightly",
        "stable_version": "2.9.0"
      },
      {
        "gpu_arch_type": "cpu",
        "gpu_arch_version": "",
        "desired_cuda": "cpu",
        "libtorch_variant": "shared-with-deps",
        "libtorch_config": "debug",
        "devtoolset": "",
        "container_image": "",
        "package_type": "libtorch",
        "build_name": "libtorch-cpu-shared-with-deps-debug",
        "validation_runner": "windows.4xlarge",
        "installation": "https://download.pytorch.org/libtorch/nightly/cpu/libtorch-win-shared-with-deps-debug-latest.zip",
        "channel": "nightly",
        "stable_version": "2.9.0"
      },
      {
        "gpu_arch_type": "cuda",
        "gpu_arch_version": "12.6",
        "desired_cuda": "cu126",
        "libtorch_variant": "shared-with-deps",
        "libtorch_config": "debug",
        "devtoolset": "",
        "container_image": "",
        "package_type": "libtorch",
        "build_name": "libtorch-cuda12_6-shared-with-deps-debug",
        "validation_runner": "windows.4xlarge",
        "installation": "https://download.pytorch.org/libtorch/nightly/cu126/libtorch-win-shared-with-deps-debug-latest.zip",
        "channel": "nightly",
        "stable_version": "2.9.0"
      },
      {
        "gpu_arch_type": "cuda",
        "gpu_arch_version": "12.8",
        "desired_cuda": "cu128",
        "libtorch_variant": "shared-with-deps",
        "libtorch_config": "debug",
        "devtoolset": "",
        "container_image": "",
        "package_type": "libtorch",
        "build_name": "libtorch-cuda12_8-shared-with-deps-debug",
        "validation_runner": "windows.4xlarge",
        "installation": "https://download.pytorch.org/libtorch/nightly/cu128/libtorch-win-shared-with-deps-debug-latest.zip",
        "channel": "nightly",
        "stable_version": "2.9.0"
      },
      {
        "gpu_arch_type": "cuda",
        "gpu_arch_version": "13.0",
        "desired_cuda": "cu130",
        "libtorch_variant": "shared-with-deps",
        "libtorch_config": "debug",
        "devtoolset": "",
        "container_image": "",
        "package_type": "libtorch",
        "build_name": "libtorch-cuda13_0-shared-with-deps-debug",
        "validation_runner": "windows.4xlarge",
        "installation": "https://download.pytorch.org/libtorch/nightly/cu130/libtorch-win-shared-with-deps-debug-latest.zip",
        "channel": "nightly",
        "stable_version": "2.9.0"
      }
    ],
    "macos": [
      {
        "python_version": "3.10",
        "gpu_arch_type": "cpu",
        "gpu_arch_version": "",
        "desired_cuda": "cpu",
        "container_image": "pytorch/manylinux2_28-builder:cpu",
        "package_type": "wheel",
        "build_name": "wheel-py3_10-cpu",
        "validation_runner": "macos-m1-stable",
        "installation": "pip3 install --pre torch torchvision --index-url https://download.pytorch.org/whl/nightly/cpu",
        "channel": "nightly",
        "upload_to_base_bucket": "no",
        "stable_version": "2.9.0"
      },
      {
        "python_version": "3.11",
        "gpu_arch_type": "cpu",
        "gpu_arch_version": "",
        "desired_cuda": "cpu",
        "container_image": "pytorch/manylinux2_28-builder:cpu",
        "package_type": "wheel",
        "build_name": "wheel-py3_11-cpu",
        "validation_runner": "macos-m1-stable",
        "installation": "pip3 install --pre torch torchvision --index-url https://download.pytorch.org/whl/nightly/cpu",
        "channel": "nightly",
        "upload_to_base_bucket": "no",
        "stable_version": "2.9.0"
      },
      {
        "python_version": "3.12",
        "gpu_arch_type": "cpu",
        "gpu_arch_version": "",
        "desired_cuda": "cpu",
        "container_image": "pytorch/manylinux2_28-builder:cpu",
        "package_type": "wheel",
        "build_name": "wheel-py3_12-cpu",
        "validation_runner": "macos-m1-stable",
        "installation": "pip3 install --pre torch torchvision --index-url https://download.pytorch.org/whl/nightly/cpu",
        "channel": "nightly",
        "upload_to_base_bucket": "no",
        "stable_version": "2.9.0"
      },
      {
        "python_version": "3.13",
        "gpu_arch_type": "cpu",
        "gpu_arch_version": "",
        "desired_cuda": "cpu",
        "container_image": "pytorch/manylinux2_28-builder:cpu",
        "package_type": "wheel",
        "build_name": "wheel-py3_13-cpu",
        "validation_runner": "macos-m1-stable",
        "installation": "pip3 install --pre torch torchvision --index-url https://download.pytorch.org/whl/nightly/cpu",
        "channel": "nightly",
        "upload_to_base_bucket": "no",
        "stable_version": "2.9.0"
      },
      {
        "python_version": "3.13t",
        "gpu_arch_type": "cpu",
        "gpu_arch_version": "",
        "desired_cuda": "cpu",
        "container_image": "pytorch/manylinux2_28-builder:cpu",
        "package_type": "wheel",
        "build_name": "wheel-py3_13t-cpu",
        "validation_runner": "macos-m1-stable",
        "installation": "pip3 install --pre torch torchvision --index-url https://download.pytorch.org/whl/nightly/cpu",
        "channel": "nightly",
        "upload_to_base_bucket": "no",
        "stable_version": "2.9.0"
      },
      {
        "python_version": "3.14",
        "gpu_arch_type": "cpu",
        "gpu_arch_version": "",
        "desired_cuda": "cpu",
        "container_image": "pytorch/manylinux2_28-builder:cpu",
        "package_type": "wheel",
        "build_name": "wheel-py3_14-cpu",
        "validation_runner": "macos-m1-stable",
        "installation": "pip3 install --pre torch torchvision --index-url https://download.pytorch.org/whl/nightly/cpu",
        "channel": "nightly",
        "upload_to_base_bucket": "no",
        "stable_version": "2.9.0"
      },
      {
        "python_version": "3.14t",
        "gpu_arch_type": "cpu",
        "gpu_arch_version": "",
        "desired_cuda": "cpu",
        "container_image": "pytorch/manylinux2_28-builder:cpu",
        "package_type": "wheel",
        "build_name": "wheel-py3_14t-cpu",
        "validation_runner": "macos-m1-stable",
        "installation": "pip3 install --pre torch torchvision --index-url https://download.pytorch.org/whl/nightly/cpu",
        "channel": "nightly",
        "upload_to_base_bucket": "no",
        "stable_version": "2.9.0"
      },
      {
        "gpu_arch_type": "cpu",
        "gpu_arch_version": "",
        "desired_cuda": "cpu",
        "libtorch_variant": "shared-with-deps",
        "libtorch_config": "",
        "devtoolset": "cxx11-abi",
        "container_image": "pytorch/libtorch-cxx11-builder:cpu",
        "package_type": "libtorch",
        "build_name": "libtorch-cpu-shared-with-deps-cxx11-abi",
        "validation_runner": "macos-m1-stable",
        "installation": "https://download.pytorch.org/libtorch/nightly/cpu/libtorch-macos-arm64-latest.zip",
        "channel": "nightly",
        "stable_version": "2.9.0"
      }
    ]
  },
  "release": {
    "linux": [
      {
        "python_version": "3.10",
        "gpu_arch_type": "cpu",
        "gpu_arch_version": "",
        "desired_cuda": "cpu",
        "container_image": "pytorch/manylinux2_28-builder:cpu",
        "package_type": "manywheel",
        "build_name": "manywheel-py3_10-cpu",
        "validation_runner": "linux.2xlarge",
        "installation": "pip3 install torch torchvision --index-url https://download.pytorch.org/whl/cpu",
        "channel": "release",
        "upload_to_base_bucket": "no",
        "stable_version": "2.9.0"
      },
      {
        "python_version": "3.10",
        "gpu_arch_type": "cuda",
        "gpu_arch_version": "12.6",
        "desired_cuda": "cu126",
        "container_image": "pytorch/manylinux2_28-builder:cuda12.6",
        "package_type": "manywheel",
        "build_name": "manywheel-py3_10-cuda12_6",
        "validation_runner": "linux.g5.4xlarge.nvidia.gpu",
        "installation": "pip3 install torch torchvision --index-url https://download.pytorch.org/whl/cu126",
        "channel": "release",
        "upload_to_base_bucket": "no",
        "stable_version": "2.9.0"
      },
      {
        "python_version": "3.10",
        "gpu_arch_type": "cuda",
        "gpu_arch_version": "12.8",
        "desired_cuda": "cu128",
        "container_image": "pytorch/manylinux2_28-builder:cuda12.8",
        "package_type": "manywheel",
        "build_name": "manywheel-py3_10-cuda12_8",
        "validation_runner": "linux.g5.4xlarge.nvidia.gpu",
        "installation": "pip3 install torch torchvision",
        "channel": "release",
        "upload_to_base_bucket": "no",
        "stable_version": "2.9.0"
      },
      {
        "python_version": "3.10",
        "gpu_arch_type": "cuda",
        "gpu_arch_version": "13.0",
        "desired_cuda": "cu130",
        "container_image": "pytorch/manylinux2_28-builder:cuda13.0",
        "package_type": "manywheel",
        "build_name": "manywheel-py3_10-cuda13_0",
        "validation_runner": "linux.g5.4xlarge.nvidia.gpu",
        "installation": "pip3 install torch torchvision --index-url https://download.pytorch.org/whl/cu130",
        "channel": "release",
        "upload_to_base_bucket": "no",
        "stable_version": "2.9.0"
      },
      {
        "python_version": "3.10",
        "gpu_arch_type": "rocm",
        "gpu_arch_version": "6.3",
        "desired_cuda": "rocm6.3",
        "container_image": "pytorch/manylinux2_28-builder:rocm6.3",
        "package_type": "manywheel",
        "build_name": "manywheel-py3_10-rocm6_3",
        "validation_runner": "linux.2xlarge",
        "installation": "pip3 install torch torchvision --index-url https://download.pytorch.org/whl/rocm6.3",
        "channel": "release",
        "upload_to_base_bucket": "no",
        "stable_version": "2.9.0"
      },
      {
        "python_version": "3.10",
        "gpu_arch_type": "rocm",
        "gpu_arch_version": "6.4",
        "desired_cuda": "rocm6.4",
        "container_image": "pytorch/manylinux2_28-builder:rocm6.4",
        "package_type": "manywheel",
        "build_name": "manywheel-py3_10-rocm6_4",
        "validation_runner": "linux.2xlarge",
        "installation": "pip3 install torch torchvision --index-url https://download.pytorch.org/whl/rocm6.4",
        "channel": "release",
        "upload_to_base_bucket": "no",
        "stable_version": "2.9.0"
      },
      {
        "python_version": "3.11",
        "gpu_arch_type": "cpu",
        "gpu_arch_version": "",
        "desired_cuda": "cpu",
        "container_image": "pytorch/manylinux2_28-builder:cpu",
        "package_type": "manywheel",
        "build_name": "manywheel-py3_11-cpu",
        "validation_runner": "linux.2xlarge",
        "installation": "pip3 install torch torchvision --index-url https://download.pytorch.org/whl/cpu",
        "channel": "release",
        "upload_to_base_bucket": "no",
        "stable_version": "2.9.0"
      },
      {
        "python_version": "3.11",
        "gpu_arch_type": "cuda",
        "gpu_arch_version": "12.6",
        "desired_cuda": "cu126",
        "container_image": "pytorch/manylinux2_28-builder:cuda12.6",
        "package_type": "manywheel",
        "build_name": "manywheel-py3_11-cuda12_6",
        "validation_runner": "linux.g5.4xlarge.nvidia.gpu",
        "installation": "pip3 install torch torchvision --index-url https://download.pytorch.org/whl/cu126",
        "channel": "release",
        "upload_to_base_bucket": "no",
        "stable_version": "2.9.0"
      },
      {
        "python_version": "3.11",
        "gpu_arch_type": "cuda",
        "gpu_arch_version": "12.8",
        "desired_cuda": "cu128",
        "container_image": "pytorch/manylinux2_28-builder:cuda12.8",
        "package_type": "manywheel",
        "build_name": "manywheel-py3_11-cuda12_8",
        "validation_runner": "linux.g5.4xlarge.nvidia.gpu",
        "installation": "pip3 install torch torchvision",
        "channel": "release",
        "upload_to_base_bucket": "no",
        "stable_version": "2.9.0"
      },
      {
        "python_version": "3.11",
        "gpu_arch_type": "cuda",
        "gpu_arch_version": "13.0",
        "desired_cuda": "cu130",
        "container_image": "pytorch/manylinux2_28-builder:cuda13.0",
        "package_type": "manywheel",
        "build_name": "manywheel-py3_11-cuda13_0",
        "validation_runner": "linux.g5.4xlarge.nvidia.gpu",
        "installation": "pip3 install torch torchvision --index-url https://download.pytorch.org/whl/cu130",
        "channel": "release",
        "upload_to_base_bucket": "no",
        "stable_version": "2.9.0"
      },
      {
        "python_version": "3.11",
        "gpu_arch_type": "rocm",
        "gpu_arch_version": "6.3",
        "desired_cuda": "rocm6.3",
        "container_image": "pytorch/manylinux2_28-builder:rocm6.3",
        "package_type": "manywheel",
        "build_name": "manywheel-py3_11-rocm6_3",
        "validation_runner": "linux.2xlarge",
        "installation": "pip3 install torch torchvision --index-url https://download.pytorch.org/whl/rocm6.3",
        "channel": "release",
        "upload_to_base_bucket": "no",
        "stable_version": "2.9.0"
      },
      {
        "python_version": "3.11",
        "gpu_arch_type": "rocm",
        "gpu_arch_version": "6.4",
        "desired_cuda": "rocm6.4",
        "container_image": "pytorch/manylinux2_28-builder:rocm6.4",
        "package_type": "manywheel",
        "build_name": "manywheel-py3_11-rocm6_4",
        "validation_runner": "linux.2xlarge",
        "installation": "pip3 install torch torchvision --index-url https://download.pytorch.org/whl/rocm6.4",
        "channel": "release",
        "upload_to_base_bucket": "no",
        "stable_version": "2.9.0"
      },
      {
        "python_version": "3.12",
        "gpu_arch_type": "cpu",
        "gpu_arch_version": "",
        "desired_cuda": "cpu",
        "container_image": "pytorch/manylinux2_28-builder:cpu",
        "package_type": "manywheel",
        "build_name": "manywheel-py3_12-cpu",
        "validation_runner": "linux.2xlarge",
        "installation": "pip3 install torch torchvision --index-url https://download.pytorch.org/whl/cpu",
        "channel": "release",
        "upload_to_base_bucket": "no",
        "stable_version": "2.9.0"
      },
      {
        "python_version": "3.12",
        "gpu_arch_type": "cuda",
        "gpu_arch_version": "12.6",
        "desired_cuda": "cu126",
        "container_image": "pytorch/manylinux2_28-builder:cuda12.6",
        "package_type": "manywheel",
        "build_name": "manywheel-py3_12-cuda12_6",
        "validation_runner": "linux.g5.4xlarge.nvidia.gpu",
        "installation": "pip3 install torch torchvision --index-url https://download.pytorch.org/whl/cu126",
        "channel": "release",
        "upload_to_base_bucket": "no",
        "stable_version": "2.9.0"
      },
      {
        "python_version": "3.12",
        "gpu_arch_type": "cuda",
        "gpu_arch_version": "12.8",
        "desired_cuda": "cu128",
        "container_image": "pytorch/manylinux2_28-builder:cuda12.8",
        "package_type": "manywheel",
        "build_name": "manywheel-py3_12-cuda12_8",
        "validation_runner": "linux.g5.4xlarge.nvidia.gpu",
        "installation": "pip3 install torch torchvision",
        "channel": "release",
        "upload_to_base_bucket": "no",
        "stable_version": "2.9.0"
      },
      {
        "python_version": "3.12",
        "gpu_arch_type": "cuda",
        "gpu_arch_version": "13.0",
        "desired_cuda": "cu130",
        "container_image": "pytorch/manylinux2_28-builder:cuda13.0",
        "package_type": "manywheel",
        "build_name": "manywheel-py3_12-cuda13_0",
        "validation_runner": "linux.g5.4xlarge.nvidia.gpu",
        "installation": "pip3 install torch torchvision --index-url https://download.pytorch.org/whl/cu130",
        "channel": "release",
        "upload_to_base_bucket": "no",
        "stable_version": "2.9.0"
      },
      {
        "python_version": "3.12",
        "gpu_arch_type": "rocm",
        "gpu_arch_version": "6.3",
        "desired_cuda": "rocm6.3",
        "container_image": "pytorch/manylinux2_28-builder:rocm6.3",
        "package_type": "manywheel",
        "build_name": "manywheel-py3_12-rocm6_3",
        "validation_runner": "linux.2xlarge",
        "installation": "pip3 install torch torchvision --index-url https://download.pytorch.org/whl/rocm6.3",
        "channel": "release",
        "upload_to_base_bucket": "no",
        "stable_version": "2.9.0"
      },
      {
        "python_version": "3.12",
        "gpu_arch_type": "rocm",
        "gpu_arch_version": "6.4",
        "desired_cuda": "rocm6.4",
        "container_image": "pytorch/manylinux2_28-builder:rocm6.4",
        "package_type": "manywheel",
        "build_name": "manywheel-py3_12-rocm6_4",
        "validation_runner": "linux.2xlarge",
        "installation": "pip3 install torch torchvision --index-url https://download.pytorch.org/whl/rocm6.4",
        "channel": "release",
        "upload_to_base_bucket": "no",
        "stable_version": "2.9.0"
      },
      {
        "python_version": "3.13",
        "gpu_arch_type": "cpu",
        "gpu_arch_version": "",
        "desired_cuda": "cpu",
        "container_image": "pytorch/manylinux2_28-builder:cpu",
        "package_type": "manywheel",
        "build_name": "manywheel-py3_13-cpu",
        "validation_runner": "linux.2xlarge",
        "installation": "pip3 install torch torchvision --index-url https://download.pytorch.org/whl/cpu",
        "channel": "release",
        "upload_to_base_bucket": "no",
        "stable_version": "2.9.0"
      },
      {
        "python_version": "3.13",
        "gpu_arch_type": "cuda",
        "gpu_arch_version": "12.6",
        "desired_cuda": "cu126",
        "container_image": "pytorch/manylinux2_28-builder:cuda12.6",
        "package_type": "manywheel",
        "build_name": "manywheel-py3_13-cuda12_6",
        "validation_runner": "linux.g5.4xlarge.nvidia.gpu",
        "installation": "pip3 install torch torchvision --index-url https://download.pytorch.org/whl/cu126",
        "channel": "release",
        "upload_to_base_bucket": "no",
        "stable_version": "2.9.0"
      },
      {
        "python_version": "3.13",
        "gpu_arch_type": "cuda",
        "gpu_arch_version": "12.8",
        "desired_cuda": "cu128",
        "container_image": "pytorch/manylinux2_28-builder:cuda12.8",
        "package_type": "manywheel",
        "build_name": "manywheel-py3_13-cuda12_8",
        "validation_runner": "linux.g5.4xlarge.nvidia.gpu",
        "installation": "pip3 install torch torchvision",
        "channel": "release",
        "upload_to_base_bucket": "no",
        "stable_version": "2.9.0"
      },
      {
        "python_version": "3.13",
        "gpu_arch_type": "cuda",
        "gpu_arch_version": "13.0",
        "desired_cuda": "cu130",
        "container_image": "pytorch/manylinux2_28-builder:cuda13.0",
        "package_type": "manywheel",
        "build_name": "manywheel-py3_13-cuda13_0",
        "validation_runner": "linux.g5.4xlarge.nvidia.gpu",
        "installation": "pip3 install torch torchvision --index-url https://download.pytorch.org/whl/cu130",
        "channel": "release",
        "upload_to_base_bucket": "no",
        "stable_version": "2.9.0"
      },
      {
        "python_version": "3.13",
        "gpu_arch_type": "rocm",
        "gpu_arch_version": "6.3",
        "desired_cuda": "rocm6.3",
        "container_image": "pytorch/manylinux2_28-builder:rocm6.3",
        "package_type": "manywheel",
        "build_name": "manywheel-py3_13-rocm6_3",
        "validation_runner": "linux.2xlarge",
        "installation": "pip3 install torch torchvision --index-url https://download.pytorch.org/whl/rocm6.3",
        "channel": "release",
        "upload_to_base_bucket": "no",
        "stable_version": "2.9.0"
      },
      {
        "python_version": "3.13",
        "gpu_arch_type": "rocm",
        "gpu_arch_version": "6.4",
        "desired_cuda": "rocm6.4",
        "container_image": "pytorch/manylinux2_28-builder:rocm6.4",
        "package_type": "manywheel",
        "build_name": "manywheel-py3_13-rocm6_4",
        "validation_runner": "linux.2xlarge",
        "installation": "pip3 install torch torchvision --index-url https://download.pytorch.org/whl/rocm6.4",
        "channel": "release",
        "upload_to_base_bucket": "no",
        "stable_version": "2.9.0"
      },
      {
        "python_version": "3.14",
        "gpu_arch_type": "cpu",
        "gpu_arch_version": "",
        "desired_cuda": "cpu",
        "container_image": "pytorch/manylinux2_28-builder:cpu",
        "package_type": "manywheel",
        "build_name": "manywheel-py3_14-cpu",
        "validation_runner": "linux.2xlarge",
        "installation": "pip3 install torch torchvision --index-url https://download.pytorch.org/whl/cpu",
        "channel": "release",
        "upload_to_base_bucket": "no",
        "stable_version": "2.9.0"
      },
      {
        "python_version": "3.14",
        "gpu_arch_type": "cuda",
        "gpu_arch_version": "12.6",
        "desired_cuda": "cu126",
        "container_image": "pytorch/manylinux2_28-builder:cuda12.6",
        "package_type": "manywheel",
        "build_name": "manywheel-py3_14-cuda12_6",
        "validation_runner": "linux.g5.4xlarge.nvidia.gpu",
        "installation": "pip3 install torch torchvision --index-url https://download.pytorch.org/whl/cu126",
        "channel": "release",
        "upload_to_base_bucket": "no",
        "stable_version": "2.9.0"
      },
      {
        "python_version": "3.14",
        "gpu_arch_type": "cuda",
        "gpu_arch_version": "12.8",
        "desired_cuda": "cu128",
        "container_image": "pytorch/manylinux2_28-builder:cuda12.8",
        "package_type": "manywheel",
        "build_name": "manywheel-py3_14-cuda12_8",
        "validation_runner": "linux.g5.4xlarge.nvidia.gpu",
        "installation": "pip3 install torch torchvision",
        "channel": "release",
        "upload_to_base_bucket": "no",
        "stable_version": "2.9.0"
      },
      {
        "python_version": "3.14",
        "gpu_arch_type": "cuda",
        "gpu_arch_version": "13.0",
        "desired_cuda": "cu130",
        "container_image": "pytorch/manylinux2_28-builder:cuda13.0",
        "package_type": "manywheel",
        "build_name": "manywheel-py3_14-cuda13_0",
        "validation_runner": "linux.g5.4xlarge.nvidia.gpu",
        "installation": "pip3 install torch torchvision --index-url https://download.pytorch.org/whl/cu130",
        "channel": "release",
        "upload_to_base_bucket": "no",
        "stable_version": "2.9.0"
      },
      {
        "python_version": "3.14",
        "gpu_arch_type": "rocm",
        "gpu_arch_version": "6.3",
        "desired_cuda": "rocm6.3",
        "container_image": "pytorch/manylinux2_28-builder:rocm6.3",
        "package_type": "manywheel",
        "build_name": "manywheel-py3_14-rocm6_3",
        "validation_runner": "linux.2xlarge",
        "installation": "pip3 install torch torchvision --index-url https://download.pytorch.org/whl/rocm6.3",
        "channel": "release",
        "upload_to_base_bucket": "no",
        "stable_version": "2.9.0"
      },
      {
        "python_version": "3.14",
        "gpu_arch_type": "rocm",
        "gpu_arch_version": "6.4",
        "desired_cuda": "rocm6.4",
        "container_image": "pytorch/manylinux2_28-builder:rocm6.4",
        "package_type": "manywheel",
        "build_name": "manywheel-py3_14-rocm6_4",
        "validation_runner": "linux.2xlarge",
        "installation": "pip3 install torch torchvision --index-url https://download.pytorch.org/whl/rocm6.4",
        "channel": "release",
        "upload_to_base_bucket": "no",
        "stable_version": "2.9.0"
      },
      {
        "python_version": "3.14t",
        "gpu_arch_type": "cpu",
        "gpu_arch_version": "",
        "desired_cuda": "cpu",
        "container_image": "pytorch/manylinux2_28-builder:cpu",
        "package_type": "manywheel",
        "build_name": "manywheel-py3_14t-cpu",
        "validation_runner": "linux.2xlarge",
        "installation": "pip3 install torch torchvision --index-url https://download.pytorch.org/whl/cpu",
        "channel": "release",
        "upload_to_base_bucket": "no",
        "stable_version": "2.9.0"
      },
      {
        "python_version": "3.14t",
        "gpu_arch_type": "cuda",
        "gpu_arch_version": "12.6",
        "desired_cuda": "cu126",
        "container_image": "pytorch/manylinux2_28-builder:cuda12.6",
        "package_type": "manywheel",
        "build_name": "manywheel-py3_14t-cuda12_6",
        "validation_runner": "linux.g5.4xlarge.nvidia.gpu",
        "installation": "pip3 install torch torchvision --index-url https://download.pytorch.org/whl/cu126",
        "channel": "release",
        "upload_to_base_bucket": "no",
        "stable_version": "2.9.0"
      },
      {
        "python_version": "3.14t",
        "gpu_arch_type": "cuda",
        "gpu_arch_version": "12.8",
        "desired_cuda": "cu128",
        "container_image": "pytorch/manylinux2_28-builder:cuda12.8",
        "package_type": "manywheel",
        "build_name": "manywheel-py3_14t-cuda12_8",
        "validation_runner": "linux.g5.4xlarge.nvidia.gpu",
        "installation": "pip3 install torch torchvision",
        "channel": "release",
        "upload_to_base_bucket": "no",
        "stable_version": "2.9.0"
      },
      {
        "python_version": "3.14t",
        "gpu_arch_type": "cuda",
        "gpu_arch_version": "13.0",
        "desired_cuda": "cu130",
        "container_image": "pytorch/manylinux2_28-builder:cuda13.0",
        "package_type": "manywheel",
        "build_name": "manywheel-py3_14t-cuda13_0",
        "validation_runner": "linux.g5.4xlarge.nvidia.gpu",
        "installation": "pip3 install torch torchvision --index-url https://download.pytorch.org/whl/cu130",
        "channel": "release",
        "upload_to_base_bucket": "no",
        "stable_version": "2.9.0"
      },
      {
        "python_version": "3.14t",
        "gpu_arch_type": "rocm",
        "gpu_arch_version": "6.3",
        "desired_cuda": "rocm6.3",
        "container_image": "pytorch/manylinux2_28-builder:rocm6.3",
        "package_type": "manywheel",
        "build_name": "manywheel-py3_14t-rocm6_3",
        "validation_runner": "linux.2xlarge",
        "installation": "pip3 install torch torchvision --index-url https://download.pytorch.org/whl/rocm6.3",
        "channel": "release",
        "upload_to_base_bucket": "no",
        "stable_version": "2.9.0"
      },
      {
        "python_version": "3.14t",
        "gpu_arch_type": "rocm",
        "gpu_arch_version": "6.4",
        "desired_cuda": "rocm6.4",
        "container_image": "pytorch/manylinux2_28-builder:rocm6.4",
        "package_type": "manywheel",
        "build_name": "manywheel-py3_14t-rocm6_4",
        "validation_runner": "linux.2xlarge",
        "installation": "pip3 install torch torchvision --index-url https://download.pytorch.org/whl/rocm6.4",
        "channel": "release",
        "upload_to_base_bucket": "no",
        "stable_version": "2.9.0"
      },
      {
        "gpu_arch_type": "cpu",
        "gpu_arch_version": "",
        "desired_cuda": "cpu",
        "libtorch_variant": "shared-with-deps",
        "libtorch_config": "",
        "devtoolset": "cxx11-abi",
        "container_image": "pytorch/libtorch-cxx11-builder:cpu",
        "package_type": "libtorch",
        "build_name": "libtorch-cpu-shared-with-deps-cxx11-abi",
        "validation_runner": "linux.2xlarge",
        "installation": "https://download.pytorch.org/libtorch/cpu/libtorch-shared-with-deps-2.9.0%2Bcpu.zip",
        "channel": "release",
        "stable_version": "2.9.0"
      },
      {
        "gpu_arch_type": "cuda",
        "gpu_arch_version": "12.6",
        "desired_cuda": "cu126",
        "libtorch_variant": "shared-with-deps",
        "libtorch_config": "",
        "devtoolset": "cxx11-abi",
        "container_image": "pytorch/libtorch-cxx11-builder:cuda12.6",
        "package_type": "libtorch",
        "build_name": "libtorch-cuda12_6-shared-with-deps-cxx11-abi",
        "validation_runner": "linux.2xlarge",
        "installation": "https://download.pytorch.org/libtorch/cu126/libtorch-shared-with-deps-2.9.0%2Bcu126.zip",
        "channel": "release",
        "stable_version": "2.9.0"
      },
      {
        "gpu_arch_type": "cuda",
        "gpu_arch_version": "12.8",
        "desired_cuda": "cu128",
        "libtorch_variant": "shared-with-deps",
        "libtorch_config": "",
        "devtoolset": "cxx11-abi",
        "container_image": "pytorch/libtorch-cxx11-builder:cuda12.8",
        "package_type": "libtorch",
        "build_name": "libtorch-cuda12_8-shared-with-deps-cxx11-abi",
        "validation_runner": "linux.2xlarge",
        "installation": "https://download.pytorch.org/libtorch/cu128/libtorch-shared-with-deps-2.9.0%2Bcu128.zip",
        "channel": "release",
        "stable_version": "2.9.0"
      },
      {
        "gpu_arch_type": "cuda",
        "gpu_arch_version": "13.0",
        "desired_cuda": "cu130",
        "libtorch_variant": "shared-with-deps",
        "libtorch_config": "",
        "devtoolset": "cxx11-abi",
        "container_image": "pytorch/libtorch-cxx11-builder:cuda13.0",
        "package_type": "libtorch",
        "build_name": "libtorch-cuda13_0-shared-with-deps-cxx11-abi",
        "validation_runner": "linux.2xlarge",
        "installation": "https://download.pytorch.org/libtorch/cu130/libtorch-shared-with-deps-2.9.0%2Bcu130.zip",
        "channel": "release",
        "stable_version": "2.9.0"
      },
      {
        "gpu_arch_type": "rocm",
        "gpu_arch_version": "6.3",
        "desired_cuda": "rocm6.3",
        "libtorch_variant": "shared-with-deps",
        "libtorch_config": "",
        "devtoolset": "cxx11-abi",
        "container_image": "pytorch/libtorch-cxx11-builder:rocm6.3",
        "package_type": "libtorch",
        "build_name": "libtorch-rocm6_3-shared-with-deps-cxx11-abi",
        "validation_runner": "linux.2xlarge",
        "installation": "https://download.pytorch.org/libtorch/rocm6.3/libtorch-shared-with-deps-2.9.0%2Brocm6.3.zip",
        "channel": "release",
        "stable_version": "2.9.0"
      },
      {
        "gpu_arch_type": "rocm",
        "gpu_arch_version": "6.4",
        "desired_cuda": "rocm6.4",
        "libtorch_variant": "shared-with-deps",
        "libtorch_config": "",
        "devtoolset": "cxx11-abi",
        "container_image": "pytorch/libtorch-cxx11-builder:rocm6.4",
        "package_type": "libtorch",
        "build_name": "libtorch-rocm6_4-shared-with-deps-cxx11-abi",
        "validation_runner": "linux.2xlarge",
        "installation": "https://download.pytorch.org/libtorch/rocm6.4/libtorch-shared-with-deps-2.9.0%2Brocm6.4.zip",
        "channel": "release",
        "stable_version": "2.9.0"
      }
    ],
    "windows": [
      {
        "python_version": "3.10",
        "gpu_arch_type": "cpu",
        "gpu_arch_version": "",
        "desired_cuda": "cpu",
        "container_image": "pytorch/manylinux2_28-builder:cpu",
        "package_type": "wheel",
        "build_name": "wheel-py3_10-cpu",
        "validation_runner": "windows.4xlarge",
        "installation": "pip3 install torch torchvision",
        "channel": "release",
        "upload_to_base_bucket": "no",
        "stable_version": "2.9.0"
      },
      {
        "python_version": "3.10",
        "gpu_arch_type": "cuda",
        "gpu_arch_version": "12.6",
        "desired_cuda": "cu126",
        "container_image": "pytorch/manylinux2_28-builder:cuda12.6",
        "package_type": "wheel",
        "build_name": "wheel-py3_10-cuda12_6",
        "validation_runner": "windows.g4dn.xlarge",
        "installation": "pip3 install torch torchvision --index-url https://download.pytorch.org/whl/cu126",
        "channel": "release",
        "upload_to_base_bucket": "no",
        "stable_version": "2.9.0"
      },
      {
        "python_version": "3.10",
        "gpu_arch_type": "cuda",
        "gpu_arch_version": "12.8",
        "desired_cuda": "cu128",
        "container_image": "pytorch/manylinux2_28-builder:cuda12.8",
        "package_type": "wheel",
        "build_name": "wheel-py3_10-cuda12_8",
        "validation_runner": "windows.g4dn.xlarge",
        "installation": "pip3 install torch torchvision --index-url https://download.pytorch.org/whl/cu128",
        "channel": "release",
        "upload_to_base_bucket": "no",
        "stable_version": "2.9.0"
      },
      {
        "python_version": "3.10",
        "gpu_arch_type": "cuda",
        "gpu_arch_version": "13.0",
        "desired_cuda": "cu130",
        "container_image": "pytorch/manylinux2_28-builder:cuda13.0",
        "package_type": "wheel",
        "build_name": "wheel-py3_10-cuda13_0",
        "validation_runner": "windows.g4dn.xlarge",
        "installation": "pip3 install torch torchvision --index-url https://download.pytorch.org/whl/cu130",
        "channel": "release",
        "upload_to_base_bucket": "no",
        "stable_version": "2.9.0"
      },
      {
        "python_version": "3.11",
        "gpu_arch_type": "cpu",
        "gpu_arch_version": "",
        "desired_cuda": "cpu",
        "container_image": "pytorch/manylinux2_28-builder:cpu",
        "package_type": "wheel",
        "build_name": "wheel-py3_11-cpu",
        "validation_runner": "windows.4xlarge",
        "installation": "pip3 install torch torchvision",
        "channel": "release",
        "upload_to_base_bucket": "no",
        "stable_version": "2.9.0"
      },
      {
        "python_version": "3.11",
        "gpu_arch_type": "cuda",
        "gpu_arch_version": "12.6",
        "desired_cuda": "cu126",
        "container_image": "pytorch/manylinux2_28-builder:cuda12.6",
        "package_type": "wheel",
        "build_name": "wheel-py3_11-cuda12_6",
        "validation_runner": "windows.g4dn.xlarge",
        "installation": "pip3 install torch torchvision --index-url https://download.pytorch.org/whl/cu126",
        "channel": "release",
        "upload_to_base_bucket": "no",
        "stable_version": "2.9.0"
      },
      {
        "python_version": "3.11",
        "gpu_arch_type": "cuda",
        "gpu_arch_version": "12.8",
        "desired_cuda": "cu128",
        "container_image": "pytorch/manylinux2_28-builder:cuda12.8",
        "package_type": "wheel",
        "build_name": "wheel-py3_11-cuda12_8",
        "validation_runner": "windows.g4dn.xlarge",
        "installation": "pip3 install torch torchvision --index-url https://download.pytorch.org/whl/cu128",
        "channel": "release",
        "upload_to_base_bucket": "no",
        "stable_version": "2.9.0"
      },
      {
        "python_version": "3.11",
        "gpu_arch_type": "cuda",
        "gpu_arch_version": "13.0",
        "desired_cuda": "cu130",
        "container_image": "pytorch/manylinux2_28-builder:cuda13.0",
        "package_type": "wheel",
        "build_name": "wheel-py3_11-cuda13_0",
        "validation_runner": "windows.g4dn.xlarge",
        "installation": "pip3 install torch torchvision --index-url https://download.pytorch.org/whl/cu130",
        "channel": "release",
        "upload_to_base_bucket": "no",
        "stable_version": "2.9.0"
      },
      {
        "python_version": "3.12",
        "gpu_arch_type": "cpu",
        "gpu_arch_version": "",
        "desired_cuda": "cpu",
        "container_image": "pytorch/manylinux2_28-builder:cpu",
        "package_type": "wheel",
        "build_name": "wheel-py3_12-cpu",
        "validation_runner": "windows.4xlarge",
        "installation": "pip3 install torch torchvision",
        "channel": "release",
        "upload_to_base_bucket": "no",
        "stable_version": "2.9.0"
      },
      {
        "python_version": "3.12",
        "gpu_arch_type": "cuda",
        "gpu_arch_version": "12.6",
        "desired_cuda": "cu126",
        "container_image": "pytorch/manylinux2_28-builder:cuda12.6",
        "package_type": "wheel",
        "build_name": "wheel-py3_12-cuda12_6",
        "validation_runner": "windows.g4dn.xlarge",
        "installation": "pip3 install torch torchvision --index-url https://download.pytorch.org/whl/cu126",
        "channel": "release",
        "upload_to_base_bucket": "no",
        "stable_version": "2.9.0"
      },
      {
        "python_version": "3.12",
        "gpu_arch_type": "cuda",
        "gpu_arch_version": "12.8",
        "desired_cuda": "cu128",
        "container_image": "pytorch/manylinux2_28-builder:cuda12.8",
        "package_type": "wheel",
        "build_name": "wheel-py3_12-cuda12_8",
        "validation_runner": "windows.g4dn.xlarge",
        "installation": "pip3 install torch torchvision --index-url https://download.pytorch.org/whl/cu128",
        "channel": "release",
        "upload_to_base_bucket": "no",
        "stable_version": "2.9.0"
      },
      {
        "python_version": "3.12",
        "gpu_arch_type": "cuda",
        "gpu_arch_version": "13.0",
        "desired_cuda": "cu130",
        "container_image": "pytorch/manylinux2_28-builder:cuda13.0",
        "package_type": "wheel",
        "build_name": "wheel-py3_12-cuda13_0",
        "validation_runner": "windows.g4dn.xlarge",
        "installation": "pip3 install torch torchvision --index-url https://download.pytorch.org/whl/cu130",
        "channel": "release",
        "upload_to_base_bucket": "no",
        "stable_version": "2.9.0"
      },
      {
        "python_version": "3.13",
        "gpu_arch_type": "cpu",
        "gpu_arch_version": "",
        "desired_cuda": "cpu",
        "container_image": "pytorch/manylinux2_28-builder:cpu",
        "package_type": "wheel",
        "build_name": "wheel-py3_13-cpu",
        "validation_runner": "windows.4xlarge",
        "installation": "pip3 install torch torchvision",
        "channel": "release",
        "upload_to_base_bucket": "no",
        "stable_version": "2.9.0"
      },
      {
        "python_version": "3.13",
        "gpu_arch_type": "cuda",
        "gpu_arch_version": "12.6",
        "desired_cuda": "cu126",
        "container_image": "pytorch/manylinux2_28-builder:cuda12.6",
        "package_type": "wheel",
        "build_name": "wheel-py3_13-cuda12_6",
        "validation_runner": "windows.g4dn.xlarge",
        "installation": "pip3 install torch torchvision --index-url https://download.pytorch.org/whl/cu126",
        "channel": "release",
        "upload_to_base_bucket": "no",
        "stable_version": "2.9.0"
      },
      {
        "python_version": "3.13",
        "gpu_arch_type": "cuda",
        "gpu_arch_version": "12.8",
        "desired_cuda": "cu128",
        "container_image": "pytorch/manylinux2_28-builder:cuda12.8",
        "package_type": "wheel",
        "build_name": "wheel-py3_13-cuda12_8",
        "validation_runner": "windows.g4dn.xlarge",
        "installation": "pip3 install torch torchvision --index-url https://download.pytorch.org/whl/cu128",
        "channel": "release",
        "upload_to_base_bucket": "no",
        "stable_version": "2.9.0"
      },
      {
        "python_version": "3.13",
        "gpu_arch_type": "cuda",
        "gpu_arch_version": "13.0",
        "desired_cuda": "cu130",
        "container_image": "pytorch/manylinux2_28-builder:cuda13.0",
        "package_type": "wheel",
        "build_name": "wheel-py3_13-cuda13_0",
        "validation_runner": "windows.g4dn.xlarge",
        "installation": "pip3 install torch torchvision --index-url https://download.pytorch.org/whl/cu130",
        "channel": "release",
        "upload_to_base_bucket": "no",
        "stable_version": "2.9.0"
      },
      {
        "python_version": "3.14",
        "gpu_arch_type": "cpu",
        "gpu_arch_version": "",
        "desired_cuda": "cpu",
        "container_image": "pytorch/manylinux2_28-builder:cpu",
        "package_type": "wheel",
        "build_name": "wheel-py3_14-cpu",
        "validation_runner": "windows.4xlarge",
        "installation": "pip3 install torch torchvision",
        "channel": "release",
        "upload_to_base_bucket": "no",
        "stable_version": "2.9.0"
      },
      {
        "python_version": "3.14",
        "gpu_arch_type": "cuda",
        "gpu_arch_version": "12.6",
        "desired_cuda": "cu126",
        "container_image": "pytorch/manylinux2_28-builder:cuda12.6",
        "package_type": "wheel",
        "build_name": "wheel-py3_14-cuda12_6",
        "validation_runner": "windows.g4dn.xlarge",
        "installation": "pip3 install torch torchvision --index-url https://download.pytorch.org/whl/cu126",
        "channel": "release",
        "upload_to_base_bucket": "no",
        "stable_version": "2.9.0"
      },
      {
        "python_version": "3.14",
        "gpu_arch_type": "cuda",
        "gpu_arch_version": "12.8",
        "desired_cuda": "cu128",
        "container_image": "pytorch/manylinux2_28-builder:cuda12.8",
        "package_type": "wheel",
        "build_name": "wheel-py3_14-cuda12_8",
        "validation_runner": "windows.g4dn.xlarge",
        "installation": "pip3 install torch torchvision --index-url https://download.pytorch.org/whl/cu128",
        "channel": "release",
        "upload_to_base_bucket": "no",
        "stable_version": "2.9.0"
      },
      {
        "python_version": "3.14",
        "gpu_arch_type": "cuda",
        "gpu_arch_version": "13.0",
        "desired_cuda": "cu130",
        "container_image": "pytorch/manylinux2_28-builder:cuda13.0",
        "package_type": "wheel",
        "build_name": "wheel-py3_14-cuda13_0",
        "validation_runner": "windows.g4dn.xlarge",
        "installation": "pip3 install torch torchvision --index-url https://download.pytorch.org/whl/cu130",
        "channel": "release",
        "upload_to_base_bucket": "no",
        "stable_version": "2.9.0"
      },
      {
        "python_version": "3.14t",
        "gpu_arch_type": "cpu",
        "gpu_arch_version": "",
        "desired_cuda": "cpu",
        "container_image": "pytorch/manylinux2_28-builder:cpu",
        "package_type": "wheel",
        "build_name": "wheel-py3_14t-cpu",
        "validation_runner": "windows.4xlarge",
        "installation": "pip3 install torch torchvision",
        "channel": "release",
        "upload_to_base_bucket": "no",
        "stable_version": "2.9.0"
      },
      {
        "python_version": "3.14t",
        "gpu_arch_type": "cuda",
        "gpu_arch_version": "12.6",
        "desired_cuda": "cu126",
        "container_image": "pytorch/manylinux2_28-builder:cuda12.6",
        "package_type": "wheel",
        "build_name": "wheel-py3_14t-cuda12_6",
        "validation_runner": "windows.g4dn.xlarge",
        "installation": "pip3 install torch torchvision --index-url https://download.pytorch.org/whl/cu126",
        "channel": "release",
        "upload_to_base_bucket": "no",
        "stable_version": "2.9.0"
      },
      {
        "python_version": "3.14t",
        "gpu_arch_type": "cuda",
        "gpu_arch_version": "12.8",
        "desired_cuda": "cu128",
        "container_image": "pytorch/manylinux2_28-builder:cuda12.8",
        "package_type": "wheel",
        "build_name": "wheel-py3_14t-cuda12_8",
        "validation_runner": "windows.g4dn.xlarge",
        "installation": "pip3 install torch torchvision --index-url https://download.pytorch.org/whl/cu128",
        "channel": "release",
        "upload_to_base_bucket": "no",
        "stable_version": "2.9.0"
      },
      {
        "python_version": "3.14t",
        "gpu_arch_type": "cuda",
        "gpu_arch_version": "13.0",
        "desired_cuda": "cu130",
        "container_image": "pytorch/manylinux2_28-builder:cuda13.0",
        "package_type": "wheel",
        "build_name": "wheel-py3_14t-cuda13_0",
        "validation_runner": "windows.g4dn.xlarge",
        "installation": "pip3 install torch torchvision --index-url https://download.pytorch.org/whl/cu130",
        "channel": "release",
        "upload_to_base_bucket": "no",
        "stable_version": "2.9.0"
      },
      {
        "gpu_arch_type": "cpu",
        "gpu_arch_version": "",
        "desired_cuda": "cpu",
        "libtorch_variant": "shared-with-deps",
        "libtorch_config": "release",
        "devtoolset": "",
        "container_image": "",
        "package_type": "libtorch",
        "build_name": "libtorch-cpu-shared-with-deps-release",
        "validation_runner": "windows.4xlarge",
        "installation": "https://download.pytorch.org/libtorch/cpu/libtorch-win-shared-with-deps-2.9.0%2Bcpu.zip",
        "channel": "release",
        "stable_version": "2.9.0"
      },
      {
        "gpu_arch_type": "cuda",
        "gpu_arch_version": "12.6",
        "desired_cuda": "cu126",
        "libtorch_variant": "shared-with-deps",
        "libtorch_config": "release",
        "devtoolset": "",
        "container_image": "",
        "package_type": "libtorch",
        "build_name": "libtorch-cuda12_6-shared-with-deps-release",
        "validation_runner": "windows.4xlarge",
        "installation": "https://download.pytorch.org/libtorch/cu126/libtorch-win-shared-with-deps-2.9.0%2Bcu126.zip",
        "channel": "release",
        "stable_version": "2.9.0"
      },
      {
        "gpu_arch_type": "cuda",
        "gpu_arch_version": "12.8",
        "desired_cuda": "cu128",
        "libtorch_variant": "shared-with-deps",
        "libtorch_config": "release",
        "devtoolset": "",
        "container_image": "",
        "package_type": "libtorch",
        "build_name": "libtorch-cuda12_8-shared-with-deps-release",
        "validation_runner": "windows.4xlarge",
        "installation": "https://download.pytorch.org/libtorch/cu128/libtorch-win-shared-with-deps-2.9.0%2Bcu128.zip",
        "channel": "release",
        "stable_version": "2.9.0"
      },
      {
        "gpu_arch_type": "cuda",
        "gpu_arch_version": "13.0",
        "desired_cuda": "cu130",
        "libtorch_variant": "shared-with-deps",
        "libtorch_config": "release",
        "devtoolset": "",
        "container_image": "",
        "package_type": "libtorch",
        "build_name": "libtorch-cuda13_0-shared-with-deps-release",
        "validation_runner": "windows.4xlarge",
        "installation": "https://download.pytorch.org/libtorch/cu130/libtorch-win-shared-with-deps-2.9.0%2Bcu130.zip",
        "channel": "release",
        "stable_version": "2.9.0"
      },
      {
        "gpu_arch_type": "cpu",
        "gpu_arch_version": "",
        "desired_cuda": "cpu",
        "libtorch_variant": "shared-with-deps",
        "libtorch_config": "debug",
        "devtoolset": "",
        "container_image": "",
        "package_type": "libtorch",
        "build_name": "libtorch-cpu-shared-with-deps-debug",
        "validation_runner": "windows.4xlarge",
        "installation": "https://download.pytorch.org/libtorch/cpu/libtorch-win-shared-with-deps-debug-2.9.0%2Bcpu.zip",
        "channel": "release",
        "stable_version": "2.9.0"
      },
      {
        "gpu_arch_type": "cuda",
        "gpu_arch_version": "12.6",
        "desired_cuda": "cu126",
        "libtorch_variant": "shared-with-deps",
        "libtorch_config": "debug",
        "devtoolset": "",
        "container_image": "",
        "package_type": "libtorch",
        "build_name": "libtorch-cuda12_6-shared-with-deps-debug",
        "validation_runner": "windows.4xlarge",
        "installation": "https://download.pytorch.org/libtorch/cu126/libtorch-win-shared-with-deps-debug-2.9.0%2Bcu126.zip",
        "channel": "release",
        "stable_version": "2.9.0"
      },
      {
        "gpu_arch_type": "cuda",
        "gpu_arch_version": "12.8",
        "desired_cuda": "cu128",
        "libtorch_variant": "shared-with-deps",
        "libtorch_config": "debug",
        "devtoolset": "",
        "container_image": "",
        "package_type": "libtorch",
        "build_name": "libtorch-cuda12_8-shared-with-deps-debug",
        "validation_runner": "windows.4xlarge",
        "installation": "https://download.pytorch.org/libtorch/cu128/libtorch-win-shared-with-deps-debug-2.9.0%2Bcu128.zip",
        "channel": "release",
        "stable_version": "2.9.0"
      },
      {
        "gpu_arch_type": "cuda",
        "gpu_arch_version": "13.0",
        "desired_cuda": "cu130",
        "libtorch_variant": "shared-with-deps",
        "libtorch_config": "debug",
        "devtoolset": "",
        "container_image": "",
        "package_type": "libtorch",
        "build_name": "libtorch-cuda13_0-shared-with-deps-debug",
        "validation_runner": "windows.4xlarge",
        "installation": "https://download.pytorch.org/libtorch/cu130/libtorch-win-shared-with-deps-debug-2.9.0%2Bcu130.zip",
        "channel": "release",
        "stable_version": "2.9.0"
      }
    ],
    "macos": [
      {
        "python_version": "3.10",
        "gpu_arch_type": "cpu",
        "gpu_arch_version": "",
        "desired_cuda": "cpu",
        "container_image": "pytorch/manylinux2_28-builder:cpu",
        "package_type": "wheel",
        "build_name": "wheel-py3_10-cpu",
        "validation_runner": "macos-m1-stable",
        "installation": "pip3 install torch torchvision",
        "channel": "release",
        "upload_to_base_bucket": "no",
        "stable_version": "2.9.0"
      },
      {
        "python_version": "3.11",
        "gpu_arch_type": "cpu",
        "gpu_arch_version": "",
        "desired_cuda": "cpu",
        "container_image": "pytorch/manylinux2_28-builder:cpu",
        "package_type": "wheel",
        "build_name": "wheel-py3_11-cpu",
        "validation_runner": "macos-m1-stable",
        "installation": "pip3 install torch torchvision",
        "channel": "release",
        "upload_to_base_bucket": "no",
        "stable_version": "2.9.0"
      },
      {
        "python_version": "3.12",
        "gpu_arch_type": "cpu",
        "gpu_arch_version": "",
        "desired_cuda": "cpu",
        "container_image": "pytorch/manylinux2_28-builder:cpu",
        "package_type": "wheel",
        "build_name": "wheel-py3_12-cpu",
        "validation_runner": "macos-m1-stable",
        "installation": "pip3 install torch torchvision",
        "channel": "release",
        "upload_to_base_bucket": "no",
        "stable_version": "2.9.0"
      },
      {
        "python_version": "3.13",
        "gpu_arch_type": "cpu",
        "gpu_arch_version": "",
        "desired_cuda": "cpu",
        "container_image": "pytorch/manylinux2_28-builder:cpu",
        "package_type": "wheel",
        "build_name": "wheel-py3_13-cpu",
        "validation_runner": "macos-m1-stable",
        "installation": "pip3 install torch torchvision",
        "channel": "release",
        "upload_to_base_bucket": "no",
        "stable_version": "2.9.0"
      },
      {
        "python_version": "3.14",
        "gpu_arch_type": "cpu",
        "gpu_arch_version": "",
        "desired_cuda": "cpu",
        "container_image": "pytorch/manylinux2_28-builder:cpu",
        "package_type": "wheel",
        "build_name": "wheel-py3_14-cpu",
        "validation_runner": "macos-m1-stable",
        "installation": "pip3 install torch torchvision",
        "channel": "release",
        "upload_to_base_bucket": "no",
        "stable_version": "2.9.0"
      },
      {
        "python_version": "3.14t",
        "gpu_arch_type": "cpu",
        "gpu_arch_version": "",
        "desired_cuda": "cpu",
        "container_image": "pytorch/manylinux2_28-builder:cpu",
        "package_type": "wheel",
        "build_name": "wheel-py3_14t-cpu",
        "validation_runner": "macos-m1-stable",
        "installation": "pip3 install torch torchvision",
        "channel": "release",
        "upload_to_base_bucket": "no",
        "stable_version": "2.9.0"
      },
      {
        "gpu_arch_type": "cpu",
        "gpu_arch_version": "",
        "desired_cuda": "cpu",
        "libtorch_variant": "shared-with-deps",
        "libtorch_config": "",
        "devtoolset": "cxx11-abi",
        "container_image": "pytorch/libtorch-cxx11-builder:cpu",
        "package_type": "libtorch",
        "build_name": "libtorch-cpu-shared-with-deps-cxx11-abi",
        "validation_runner": "macos-m1-stable",
        "installation": "https://download.pytorch.org/libtorch/cpu/libtorch-macos-arm64-2.9.0.zip",
        "channel": "release",
        "stable_version": "2.9.0"
      }
    ]
  }
}